Workbook

Sheet 說明
A1: 114Q4 選案清單（全市場）— 自足驗證版
A3: 母體：listdata auditor 快照（MOPS 簽證申報）＝2681 筆
A4: （含上市/上櫃/興櫃/公開發行；證券期貨商因個體＋合併雙申報可能重複兩列）。
A5: 會計師A/B、查核意見、簽證日期＝該季申報當時之簽章資訊（非現時點狀態）。
A7: 權數分數：證交所／櫃買中心 114Q4 平時管理權數統計表（本檔內嵌原始表，逐分可追溯）。
A8: 匹配 1827 筆有分數；其餘 854 筆（公發、興櫃、金融、上市KY 等）無權數沉底、不刪除。
A9: 財務權數/非財務權數欄＝INDEX+MATCH 公式即時取自內嵌原始表；權數總計＝兩者相加；
A10: 檢核欄＝總計−原表權數總計，應全為 0（≠0 自動標紅）＝開檔即可驗證的勾稽證明。
A11: ★原始表欄84表頭誤標「權數總計」，實為非財務合計；真總計在欄85（合併表頭）。腳本用固定索引取數。
A13: 主要扣分項目(分數)：由原始表財務 9 類＋非財務 17 項之得分欄彙整（>0 者，分數高→低，名稱截18字）。
A14: 備註欄自動標記：新承接（意見含「前期由其他會計師查核」→審計510 期初餘額）；KY。
A16: 其他欄位來源：承辦人＝district.csv（證期局管區）；董事長/地址＝MOPS 公司基本資料；
... A21: 產製：2026-07-16；腳本＝make_selection_list.py（含邏輯說明，改動前先讀 docstring）。

Sheet 114Q4選案清單
A1: 市場別 | B1: 公司代號 | C1: 公司簡稱 | D1: 承辦人 | E1: 董事長 | F1: 地址 | G1: 事務所 | H1: 會計師A | I1: 會計師B | J1: 每股盈餘(元) | K1: 每股淨值(元) | L1: 查核意見 | M1: 簽證日期 | N1: 財務權數 | O1: 非財務權數 | P1: 權數總計 | Q1: 檢核(與原表總計差) | R1: 主要扣分項目(分數) | S1: 備註
A2: 上市 | B2: 6806 | C2: 森崴能源 | D2: 林抒真 | E2: 郭台強 | F2: 新北市土城區中央路四段49號 | G2: 資誠聯合會計師事務所 | H2: 周筱姿 | I2: 陳啟東 | J2: -60 | K2: 5.11 | L2: 無保留意見(繼續經營有關之重大不確定性)-繼續經營能力存在重大不確定性/繼續經營假設存有重大疑慮 | M2: 115/03/30 | N2: =IFERROR(INDEX('權數表原始_上市114Q4'!$BN:$BN,MATCH(VALUE($B2),'權數表原始_上市114Q4'!$A:$A,0)),"") | O2: =IFERROR(INDEX('權數表原始_上市114Q4'!$CF:$CF,MATCH(VALUE($B2),'權數表原始_上市114Q4'!$A:$A,0)),"") | P2: =N2+O2 | Q2: =P2-IFERROR(INDEX('權數表原始_上市114Q4'!$CG:$CG,MATCH(VALUE($B2),'權數表原始_上市114Q4'!$A:$A,0)),"") | R2: 財務比率不佳(80)；資金貸於他人(40)；非流動之股權投資占權益比重較高(30)；營業收入、營業利益或稅前純益變動較大(26)；最近一年內有訴訟事件對公司財務業務有(20)；關係企業之交易(15)；背書保證(15)；每股淨值偏低(10)；董監事持股異動(10)；總經理辭職(10)；董事辭職(5)
A3: 上櫃 | B3: 4804 | C3: 大略-KY | D3: 靖雅代伯強 | E3: 蔡輝明 | F3: 臺北市中山區南京東路2段101號11樓 | G3: 馬施云大華聯合會計師事務所 | H3: 吳昆益 | I3: 趙翊棋 | J3: -1.54 | K3: 1.02 | L3: 無保留意見(繼續經營有關之重大不確定性)-繼續經營能力存在重大不確定性/繼續經營假設存有重大疑慮 | M3: 115/03/31 | N3: =IFERROR(INDEX('權數表原始_上櫃114Q4'!$BN:$BN,MATCH(VALUE($B3),'權數表原始_上櫃114Q4'!$A:$A,0)),"") | O3: =IFERROR(INDEX('權數表原始_上櫃114Q4'!$CF:$CF,MATCH(VALUE($B3),'權數表原始_上櫃114Q4'!$A:$A,0)),"") | P3: =N3+O3 | Q3: =P3-IFERROR(INDEX('權數表原始_上櫃114Q4'!$CG:$CG,MATCH(VALUE($B3),'權數表原始_上櫃114Q4'!$A:$A,0)),"") | R3: 財務比率不佳(55)；資金貸於他人(35)；非流動之股權投資占權益比重較高(30)；會計主管辭職(20)；每股淨值偏低(15)；內稽主管辭職(10)；董事長辭職(10)；總經理辭職(10)；獨立董事辭職(10)；營業收入、營業利益或稅前純益變動較大(7)；董事辭職(5) | S3: KY
A4: 上櫃 | B4: 8444 | C4: 綠河-KY | D4: 張怡真 | E4: 謝榮輝 | F4: 222 Moo 4, T.Thachang, A.Bangklum, Songkhla, Thailand | G4: 安侯建業聯合會計師事務所 | H4: 張純怡 | I4: 江家齊 | J4: -10.06 | K4: 3.49 | L4: 無保留意見(繼續經營有關之重大不確定性)-繼續經營能力存在重大不確定性/繼續經營假設存有重大疑慮 | M4: 115/03/13 | N4: =IFERROR(INDEX('權數表原始_上櫃114Q4'!$BN:$BN,MATCH(VALUE($B4),'權數表原始_上櫃114Q4'!$A:$A,0)),"") | O4: =IFERROR(INDEX('權數表原始_上櫃114Q4'!$CF:$CF,MATCH(VALUE($B4),'權數表原始_上櫃114Q4'!$A:$A,0)),"") | P4: =N4+O4 | Q4: =P4-IFERROR(INDEX('權數表原始_上櫃114Q4'!$CG:$CG,MATCH(VALUE($B4),'權數表原始_上櫃114Q4'!$A:$A,0)),"") | R4: 財務比率不佳(80)；資金貸於他人(40)；背書保證(35)；每股淨值偏低(15)；董事長質權設定達其實際持有股數五O%(15)；營業收入、營業利益或稅前純益變動較大(14) | S4: KY
A5: 上市 | B5: 3041 | C5: 揚智 | D5: 曾冠程 | E5: 凃俊光 | F5: 台北市內湖區內湖路一段246號6樓 | G5: 安永聯合會計師事務所 | H5: 林秀青 | I5: 呂倩雯 | J5: -3.43 | K5: 10.03 | L5: 無保留意見(強調事項或其他事項) | M5: 115/03/31 | N5: =IFERROR(INDEX('權數表原始_上市114Q4'!$BN:$BN,MATCH(VALUE($B5),'權數表原始_上市114Q4'!$A:$A,0)),"") | O5: =IFERROR(INDEX('權數表原始_上市114Q4'!$CF:$CF,MATCH(VALUE($B5),'權數表原始_上市114Q4'!$A:$A,0)),"") | P5: =N5+O5 | Q5: =P5-IFERROR(INDEX('權數表原始_上市114Q4'!$CG:$CG,MATCH(VALUE($B5),'權數表原始_上市114Q4'!$A:$A,0)),"") | R5: 財務比率不佳(65)；關係企業之交易(30)；營業收入、營業利益或稅前純益變動較大(25)；非流動之股權投資占權益比重較高(20)；更換會計師（非屬會計師事務所內部調整(20)；資金貸於他人(10)；董事長辭職(10)；董事辭職(5)；董事、監察人質權設定達全體董監實際持(5)；董事長質權設定達其實際持有股數五O%(5)
A6: 上櫃 | B6: 4502 | C6: 健信 | D6: 張馨云 | E6: 吳明燦 | F6: 彰化縣線西鄉彰濱東一路3號 | G6: 資誠聯合會計師事務所 | H6: 王玉娟 | I6: 吳松源 | J6: -1.51 | K6: 9.63 | L6: 無保留意見 | M6: 115/03/16 | N6: =IFERROR(INDEX('權數表原始_上櫃114Q4'!$BN:$BN,MATCH(VALUE($B6),'權數表原始_上櫃114Q4'!$A:$A,0)),"") | O6: =IFERROR(INDEX('權數表原始_上櫃114Q4'!$CF:$CF,MATCH(VALUE($B6),'權數表原始_上櫃114Q4'!$A:$A,0)),"") | P6: =N6+O6 | Q6: =P6-IFERROR(INDEX('權數表原始_上櫃114Q4'!$CG:$CG,MATCH(VALUE($B6),'權數表原始_上櫃114Q4'!$A:$A,0)),"") | R6: 財務比率不佳(50)；營業收入、營業利益或稅前純益變動較大(26)；董事、監察人質權設定達全體董監實際持(25)；董事長質權設定達其實際持有股數五O%(25)；資金貸於他人(20)；非流動之股權投資占權益比重較高(20)；背書保證(15)；每股淨值偏低(5)
A7: 上市 | B7: 1441 | C7: 大東 | D7: 黃冠達 | E7: 陳修忠 | F7: 台北市松山區南京東路三段346號3樓 | G7: 資誠聯合會計師事務所 | H7: 林雅慧 | I7: 林永智 | J7: -0.45 | K7: 6.46 | L7: 無保留意見(強調事項或其他事項)-採用其他會計師查核(核閱)報告且欲區分責任 | M7: 115/03/11 | N7: =IFERROR(INDEX('權數表原始_上市114Q4'!$BN:$BN,MATCH(VALUE($B7),'權數表原始_上市114Q4'!$A:$A,0)),"") | O7: =IFERROR(INDEX('權數表原始_上市114Q4'!$CF:$CF,MATCH(VALUE($B7),'權數表原始_上市114Q4'!$A:$A,0)),"") | P7: =N7+O7 | Q7: =P7-IFERROR(INDEX('權數表原始_上市114Q4'!$CG:$CG,MATCH(VALUE($B7),'權數表原始_上市114Q4'!$A:$A,0)),"") | R7: 採用權益法之關聯企業及合資損益份額((30)；非流動之股權投資占權益比重較高(30)；財務比率不佳(25)；營業收入、營業利益或稅前純益變動較大(21)；財務主管辭職(20)；會計主管辭職(20)；背書保證(15)；資金貸於他人(10)；每股淨值偏低(10)
A8: 上市 | B8: 3712 | C8: 永崴投控 | D8: 張馨云 | E8: 郭台強 | F8: 新北市土城區中央路四段49號 | G8: 資誠聯合會計師事務所 | H8: 周筱姿 | I8: 林冠宏 | J8: -22.85 | K8: 13.46 | L8: 無保留意見(強調事項或其他事項)-採用其他會計師查核(核閱)報告且欲區分責任 | M8: 115/03/30 | N8: =IFERROR(INDEX('權數表原始_上市114Q4'!$BN:$BN,MATCH(VALUE($B8),'權數表原始_上市114Q4'!$A:$A,0)),"") | O8: =IFERROR(INDEX('權數表原始_上市114Q4'!$CF:$CF,MATCH(VALUE($B8),'權數表原始_上市114Q4'!$A:$A,0)),"") | P8: =N8+O8 | Q8: =P8-IFERROR(INDEX('權數表原始_上市114Q4'!$CG:$CG,MATCH(VALUE($B8),'權數表原始_上市114Q4'!$A:$A,0)),"") | R8: 財務比率不佳(70)；資金貸於他人(40)；非流動之股權投資占權益比重較高(30)；營業收入、營業利益或稅前純益變動較大(25)；背書保證(15)
A9: 上櫃 | B9: 1591 | C9: 駿吉-KY | D9: 詹孟真 | E9: 胡德立 | F9: Suite 102, Cannon Place, North Sound Rd., George Town | G9: 安侯建業聯合會計師事務所 | H9: 陳明輝 | I9: 張肇文 | J9: -2.75 | K9: 12.67 | L9: 無保留意見(強調事項或其他事項)-前期由其他會計師查核 | M9: 115/03/26 | N9: =IFERROR(INDEX('權數表原始_上櫃114Q4'!$BN:$BN,MATCH(VALUE($B9),'權數表原始_上櫃114Q4'!$A:$A,0)),"") | O9: =IFERROR(INDEX('權數表原始_上櫃114Q4'!$CF:$CF,MATCH(VALUE($B9),'權數表原始_上櫃114Q4'!$A:$A,0)),"") | P9: =N9+O9 | Q9: =P9-IFERROR(INDEX('權數表原始_上櫃114Q4'!$CG:$CG,MATCH(VALUE($B9),'權數表原始_上櫃114Q4'!$A:$A,0)),"") | R9: 財務比率不佳(60)；營業收入、營業利益或稅前純益變動較大(27)；財務主管辭職(20)；會計主管辭職(20)；背書保證(15)；內稽主管辭職(10)；董事長辭職(10)；總經理辭職(10)；董事辭職(5) | S9: 新承接（審計510 期初餘額）；KY
A10: 上市 | B10: 9906 | C10: 欣巴巴 | D10: 靖雅代光遙 | E10: 張宏圖 | F10: 高雄市前鎮區民權二路6號27樓 | G10: 安永聯合會計師事務所 | H10: 陳政初 | I10: 李芳文 | J10: 0.09 | K10: 14.89 | L10: 無保留意見 | M10: 115/02/24 | N10: =IFERROR(INDEX('權數表原始_上市114Q4'!$BN:$BN,MATCH(VALUE($B10),'權數表原始_上市114Q4'!$A:$A,0)),"") | O10: =IFERROR(INDEX('權數表原始_上市114Q4'!$CF:$CF,MATCH(VALUE($B10),'權數表原始_上市114Q4'!$A:$A,0)),"") | P10: =N10+O10 | Q10: =P10-IFERROR(INDEX('權數表原始_上市114Q4'!$CG:$CG,MATCH(VALUE($B10),'權數表原始_上市114Q4'!$A:$A,0)),"") | R10: 財務比率不佳(70)；資金貸於他人(30)；營業收入、營業利益或稅前純益變動較大(26)；會計主管辭職(20)；背書保證(15)；內稽主管辭職(10)；關係企業之交易(5)
A11: 上櫃 | B11: 3272 | C11: 東碩 | D11: 邱棕晉 | E11: 曹賜正 | F11: 新北市新店區寶橋路235巷131號3樓之4 | G11: 資誠聯合會計師事務所 | H11: 于智帆 | I11: 黃世鈞 | J11: -7.65 | K11: 16.13 | L11: 無保留意見(強調事項或其他事項)-採用其他會計師查核(核閱)報告且欲區分責任 | M11: 115/03/24 | N11: =IFERROR(INDEX('權數表原始_上櫃114Q4'!$BN:$BN,MATCH(VALUE($B11),'權數表原始_上櫃114Q4'!$A:$A,0)),"") | O11: =IFERROR(INDEX('權數表原始_上櫃114Q4'!$CF:$CF,MATCH(VALUE($B11),'權數表原始_上櫃114Q4'!$A:$A,0)),"") | P11: =N11+O11 | Q11: =P11-IFERROR(INDEX('權數表原始_上櫃114Q4'!$CG:$CG,MATCH(VALUE($B11),'權數表原始_上櫃114Q4'!$A:$A,0)),"") | R11: 財務比率不佳(40)；財務主管辭職(20)；會計主管辭職(20)；財務主管或會計主管或內稽主管是否與董(20)；營業收入、營業利益或稅前純益變動較大(19)；關係企業之交易(16)；資金貸於他人(10)；內稽主管辭職(10)；總經理辭職(10)；背書保證(5)
A12: 上櫃 | B12: 6219 | C12: 富旺 | D12: 徐雅琳 | E12: 林宗毅 | F12: 台中市西區大隆路20號4樓之5 | G12: 資誠聯合會計師事務所 | H12: 劉美蘭 | I12: 王玉娟 | J12: -0.76 | K12: 15.92 | L12: 無保留意見 | M12: 115/03/12 | N12: =IFERROR(INDEX('權數表原始_上櫃114Q4'!$BN:$BN,MATCH(VALUE($B12),'權數表原始_上櫃114Q4'!$A:$A,0)),"") | O12: =IFERROR(INDEX('權數表原始_上櫃114Q4'!$CF:$CF,MATCH(VALUE($B12),'權數表原始_上櫃114Q4'!$A:$A,0)),"") | P12: =N12+O12 | Q12: =P12-IFERROR(INDEX('權數表原始_上櫃114Q4'!$CG:$CG,MATCH(VALUE($B12),'權數表原始_上櫃114Q4'!$A:$A,0)),"") | R12: 財務比率不佳(70)；董事長質權設定達其實際持有股數五O%(25)；總經理質權設定達其實際持有股數五O%(25)；營業收入、營業利益或稅前純益變動較大(24)；會計主管辭職(20)；關係企業之交易(5)
A13: 上市 | B13: 3032 | C13: 偉訓 | D13: 李靜平 | E13: 王駿東 | F13: 台南市安南區安和路二段54巷225號 | G13: 勤業眾信聯合會計師事務所 | H13: 王騰葦 | I13: 李季珍 | J13: -7.93 | K13: 21.99 | L13: 無保留意見(強調事項或其他事項)-採用其他會計師查核(核閱)報告且欲區分責任 | M13: 115/03/12 | N13: =IFERROR(INDEX('權數表原始_上市114Q4'!$BN:$BN,MATCH(VALUE($B13),'權數表原始_上市114Q4'!$A:$A,0)),"") | O13: =IFERROR(INDEX('權數表原始_上市114Q4'!$CF:$CF,MATCH(VALUE($B13),'權數表原始_上市114Q4'!$A:$A,0)),"") | P13: =N13+O13 | Q13: =P13-IFERROR(INDEX('權數表原始_上市114Q4'!$CG:$CG,MATCH(VALUE($B13),'權數表原始_上市114Q4'!$A:$A,0)),"") | R13: 財務比率不佳(65)；資金貸於他人(40)；營業收入、營業利益或稅前純益變動較大(28)；最近一年內有訴訟事件對公司財務業務有(20)；背書保證(15)
A14: 上櫃 | B14: 4416 | C14: 三圓 | D14: 申宛云 | E14: 王雅麟 | F14: (104)台北市南京東路二段96號8樓 | G14: 集智聯合會計師事務所 | H14: 林書銘 | I14: 張俊德 | J14: -0.64 | K14: 23.4 | L14: 無保留意見(強調事項或其他事項)-採用其他會計師查核(核閱)報告且欲區分責任 | M14: 115/03/11 | N14: =IFERROR(INDEX('權數表原始_上櫃114Q4'!$BN:$BN,MATCH(VALUE($B14),'權數表原始_上櫃114Q4'!$A:$A,0)),"") | O14: =IFERROR(INDEX('權數表原始_上櫃114Q4'!$CF:$CF,MATCH(VALUE($B14),'權數表原始_上櫃114Q4'!$A:$A,0)),"") | P14: =N14+O14 | Q14: =P14-IFERROR(INDEX('權數表原始_上櫃114Q4'!$CG:$CG,MATCH(VALUE($B14),'權數表原始_上櫃114Q4'!$A:$A,0)),"") | R14: 財務比率不佳(65)；營業收入、營業利益或稅前純益變動較大(30)；會計主管辭職(20)；最近一年內有訴訟事件對公司財務業務有(20)；資金貸於他人(10)；董監事持股異動(10)；關係企業之交易(8)；董事辭職(5)
A15: 上市 | B15: 2601 | C15: 益航 | D15: 郭秀春 | E15: 郭人豪 | F15: 台北市復興南路二段237號14樓 | G15: 安侯建業聯合會計師事務所 | H15: 潘俊名 | I15: 張淑瑩 | J15: -1.63 | K15: 8.93 | L15: 無保留意見(強調事項或其他事項)-採用其他會計師查核(核閱)報告且欲區分責任 | M15: 115/03/30 | N15: =IFERROR(INDEX('權數表原始_上市114Q4'!$BN:$BN,MATCH(VALUE($B15),'權數表原始_上市114Q4'!$A:$A,0)),"") | O15: =IFERROR(INDEX('權數表原始_上市114Q4'!$CF:$CF,MATCH(VALUE($B15),'權數表原始_上市114Q4'!$A:$A,0)),"") | P15: =N15+O15 | Q15: =P15-IFERROR(INDEX('權數表原始_上市114Q4'!$CG:$CG,MATCH(VALUE($B15),'權數表原始_上市114Q4'!$A:$A,0)),"") | R15: 董事長質權設定達其實際持有股數五O%(25)；營業收入、營業利益或稅前純益變動較大(20)；資金貸於他人(20)；會計主管辭職(20)；關係企業之交易(15)；背書保證(15)；財務比率不佳(15)；非流動之股權投資占權益比重較高(10)；當期非流動之股權投資增減金額占權益比(10)；總經理辭職(10)；每股淨值偏低(5)
A16: 上市 | B16: 2392 | C16: 正崴 | D16: 黃靖雅 | E16: 郭台強 | F16: 新北市土城區中山路18號 | G16: 資誠聯合會計師事務所 | H16: 周筱姿 | I16: 林冠宏 | J16: -6.62 | K16: 47.56 | L16: 無保留意見(強調事項或其他事項)-採用其他會計師查核(核閱)報告且欲區分責任 | M16: 115/03/31 | N16: =IFERROR(INDEX('權數表原始_上市114Q4'!$BN:$BN,MATCH(VALUE($B16),'權數表原始_上市114Q4'!$A:$A,0)),"") | O16: =IFERROR(INDEX('權數表原始_上市114Q4'!$CF:$CF,MATCH(VALUE($B16),'權數表原始_上市114Q4'!$A:$A,0)),"") | P16: =N16+O16 | Q16: =P16-IFERROR(INDEX('權數表原始_上市114Q4'!$CG:$CG,MATCH(VALUE($B16),'權數表原始_上市114Q4'!$A:$A,0)),"") | R16: 財務比率不佳(65)；資金貸於他人(40)；營業收入、營業利益或稅前純益變動較大(22)；非流動之股權投資占權益比重較高(20)；背書保證(15)
A17: 上市 | B17: 1909 | C17: 榮成 | D17: 嘉衛代若瑛 | E17: 鄭瑛彬 | F17: 彰化縣二林鎮廣興里廣興巷1-1號 | G17: 立本台灣聯合會計師事務所 | H17: 張宜鈞 | I17: 程建憲 | J17: -0.39 | K17: 15.54 | L17: 無保留意見 | M17: 115/03/11 | N17: =IFERROR(INDEX('權數表原始_上市114Q4'!$BN:$BN,MATCH(VALUE($B17),'權數表原始_上市114Q4'!$A:$A,0)),"") | O17: =IFERROR(INDEX('權數表原始_上市114Q4'!$CF:$CF,MATCH(VALUE($B17),'權數表原始_上市114Q4'!$A:$A,0)),"") | P17: =N17+O17 | Q17: =P17-IFERROR(INDEX('權數表原始_上市114Q4'!$CG:$CG,MATCH(VALUE($B17),'權數表原始_上市114Q4'!$A:$A,0)),"") | R17: 財務比率不佳(55)；採用權益法之關聯企業及合資損益份額((40)；資金貸於他人(40)；背書保證(15)；營業收入、營業利益或稅前純益變動較大(10)
A18: 上市 | B18: 2527 | C18: 宏璟 | D18: 張怡真 | E18: 簡文祥 | F18: 台北市基隆路一段420號10樓 | G18: 勤業眾信聯合會計師事務所 | H18: 林旺生 | I18: 施俊弘 | J18: 0.93 | K18: 65.52 | L18: 無保留意見 | M18: 115/03/06 | N18: =IFERROR(INDEX('權數表原始_上市114Q4'!$BN:$BN,MATCH(VALUE($B18),'權數表原始_上市114Q4'!$A:$A,0)),"") | O18: =IFERROR(INDEX('權數表原始_上市114Q4'!$CF:$CF,MATCH(VALUE($B18),'權數表原始_上市114Q4'!$A:$A,0)),"") | P18: =N18+O18 | Q18: =P18-IFERROR(INDEX('權數表原始_上市114Q4'!$CG:$CG,MATCH(VALUE($B18),'權數表原始_上市114Q4'!$A:$A,0)),"") | R18: 財務比率不佳(55)；關係企業之交易(30)；非流動之股權投資占權益比重較高(30)；營業收入、營業利益或稅前純益變動較大(24)；當期非流動之股權投資增減金額占權益比(20)
A19: 上櫃 | B19: 6264 | C19: 富裔 | D19: 郭秀春 | E19: 祝文定 | F19: 台北市信義區松仁路277號18樓 | G19: 勤業眾信聯合會計師事務所 | H19: 莊文源 | I19: 楊清鎮 | J19: -0.5 | K19: 5.24 | L19: 無保留意見 | M19: 115/03/30 | N19: =IFERROR(INDEX('權數表原始_上櫃114Q4'!$BN:$BN,MATCH(VALUE($B19),'權數表原始_上櫃114Q4'!$A:$A,0)),"") | O19: =IFERROR(INDEX('權數表原始_上櫃114Q4'!$CF:$CF,MATCH(VALUE($B19),'權數表原始_上櫃114Q4'!$A:$A,0)),"") | P19: =N19+O19 | Q19: =P19-IFERROR(INDEX('權數表原始_上櫃114Q4'!$CG:$CG,MATCH(VALUE($B19),'權數表原始_上櫃114Q4'!$A:$A,0)),"") | R19: 財務比率不佳(85)；營業收入、營業利益或稅前純益變動較大(27)；資金貸於他人(15)；背書保證(10)；每股淨值偏低(10)；內稽主管辭職(10)
A20: 上市 | B20: 2023 | C20: 燁輝 | D20: 黃姵蓉 | E20: 林義守 | F20: 高雄市橋頭區芋寮路369號 | G20: 國富浩華聯合會計師事務所 | H20: 郭怡伶 | I20: 黃鈴雯 | J20: -1.85 | K20: 17.42 | L20: 無保留意見(強調事項或其他事項)-採用其他會計師查核(核閱)報告且欲區分責任 | M20: 115/03/06 | N20: =IFERROR(INDEX('權數表原始_上市114Q4'!$BN:$BN,MATCH(VALUE($B20),'權數表原始_上市114Q4'!$A:$A,0)),"") | O20: =IFERROR(INDEX('權數表原始_上市114Q4'!$CF:$CF,MATCH(VALUE($B20),'權數表原始_上市114Q4'!$A:$A,0)),"") | P20: =N20+O20 | Q20: =P20-IFERROR(INDEX('權數表原始_上市114Q4'!$CG:$CG,MATCH(VALUE($B20),'權數表原始_上市114Q4'!$A:$A,0)),"") | R20: 採用權益法之關聯企業及合資損益份額((50)；非流動之股權投資占權益比重較高(30)；財務比率不佳(25)；營業收入、營業利益或稅前純益變動較大(17)；關係企業之交易(15)；資金貸於他人(15)
A21: 上櫃 | B21: 4419 | C21: 皇家美食 | D21: 佩琳代若瑛 | E21: 侯佑霖 | F21: 臺南市安平區永華路2段248號15樓之6 | G21: 安侯建業聯合會計師事務所 | H21: 高鈺倫 | I21: 張淑瑩 | J21: -1.45 | K21: 5.95 | L21: 無保留意見(強調事項或其他事項)-採用其他會計師查核(核閱)報告且欲區分責任 | M21: 115/03/06 | N21: =IFERROR(INDEX('權數表原始_上櫃114Q4'!$BN:$BN,MATCH(VALUE($B21),'權數表原始_上櫃114Q4'!$A:$A,0)),"") | O21: =IFERROR(INDEX('權數表原始_上櫃114Q4'!$CF:$CF,MATCH(VALUE($B21),'權數表原始_上櫃114Q4'!$A:$A,0)),"") | P21: =N21+O21 | Q21: =P21-IFERROR(INDEX('權數表原始_上櫃114Q4'!$CG:$CG,MATCH(VALUE($B21),'權數表原始_上櫃114Q4'!$A:$A,0)),"") | R21: 財務比率不佳(45)；營業收入、營業利益或稅前純益變動較大(27)；財務主管辭職(20)；會計主管辭職(20)；每股淨值偏低(10)；內稽主管辭職(10)；董事長辭職(10)；總經理辭職(10)
A22: 上市 | B22: 5531 | C22: 鄉林 | D22: 林抒真 | E22: 賴正鎰 | F22: 台中市西區台灣大道二段408號 | G22: 國富浩華聯合會計師事務所 | H22: 洪淑芬 | I22: 蕭又文 | J22: -0.28 | K22: 10.07 | L22: 無保留意見 | M22: 115/03/06 | N22: =IFERROR(INDEX('權數表原始_上市114Q4'!$BN:$BN,MATCH(VALUE($B22),'權數表原始_上市114Q4'!$A:$A,0)),"") | O22: =IFERROR(INDEX('權數表原始_上市114Q4'!$CF:$CF,MATCH(VALUE($B22),'權數表原始_上市114Q4'!$A:$A,0)),"") | P22: =N22+O22 | Q22: =P22-IFERROR(INDEX('權數表原始_上市114Q4'!$CG:$CG,MATCH(VALUE($B22),'權數表原始_上市114Q4'!$A:$A,0)),"") | R22: 財務比率不佳(80)；背書保證(25)；營業收入、營業利益或稅前純益變動較大(16)；資金貸於他人(10)；董事、監察人質權設定達全體董監實際持(10)；董事長質權設定達其實際持有股數五O%(10)
A23: 上市 | B23: 2429 | C23: 銘旺科 | D23: 張馨云 | E23: 周維昆 | F23: 桃園市中壢區高鐵站前西路一段286號3樓之1 | G23: 勤業眾信聯合會計師事務所 | H23: 蘇定堅 | I23: 王翔民 | J23: -1.4 | K23: 9.02 | L23: 無保留意見(強調事項或其他事項)-前期由其他會計師查核 | M23: 115/03/12 | N23: =IFERROR(INDEX('權數表原始_上市114Q4'!$BN:$BN,MATCH(VALUE($B23),'權數表原始_上市114Q4'!$A:$A,0)),"") | O23: =IFERROR(INDEX('權數表原始_上市114Q4'!$CF:$CF,MATCH(VALUE($B23),'權數表原始_上市114Q4'!$A:$A,0)),"") | P23: =N23+O23 | Q23: =P23-IFERROR(INDEX('權數表原始_上市114Q4'!$CG:$CG,MATCH(VALUE($B23),'權數表原始_上市114Q4'!$A:$A,0)),"") | R23: 財務比率不佳(45)；關係企業之交易(35)；會計主管辭職(20)；資金貸於他人(15)；背書保證(15)；營業收入、營業利益或稅前純益變動較大(10)；每股淨值偏低(5)；董監事持股異動(5) | S23: 新承接（審計510 期初餘額）
A24: 上櫃 | B24: 3064 | C24: 泰偉 | D24: 郭秀春 | E24: 林國泰 | F24: 新北市三重區興德路111-1號10樓 | G24: 安永聯合會計師事務所 | H24: 楊弘斌 | I24: 徐榮煌 | J24: -3.51 | K24: 4.63 | L24: 無保留意見 | M24: 115/03/06 | N24: =IFERROR(INDEX('權數表原始_上櫃114Q4'!$BN:$BN,MATCH(VALUE($B24),'權數表原始_上櫃114Q4'!$A:$A,0)),"") | O24: =IFERROR(INDEX('權數表原始_上櫃114Q4'!$CF:$CF,MATCH(VALUE($B24),'權數表原始_上櫃114Q4'!$A:$A,0)),"") | P24: =N24+O24 | Q24: =P24-IFERROR(INDEX('權數表原始_上櫃114Q4'!$CG:$CG,MATCH(VALUE($B24),'權數表原始_上櫃114Q4'!$A:$A,0)),"") | R24: 財務比率不佳(85)；營業收入、營業利益或稅前純益變動較大(25)；每股淨值偏低(15)；董監事持股異動(15)；非流動之股權投資占權益比重較高(10)
A25: 上市 | B25: 2438 | C25: 翔耀 | D25: 張怡真 | E25: 林以山 | F25: 臺北市大安區光復南路438號12樓 | G25: 國富浩華聯合會計師事務所 | H25: 鄭翔宇 | I25: 陳昭惠 | J25: -2.38 | K25: 5.21 | L25: 無保留意見(強調事項或其他事項)-採用其他會計師查核(核閱)報告且欲區分責任 | M25: 115/03/12 | N25: =IFERROR(INDEX('權數表原始_上市114Q4'!$BN:$BN,MATCH(VALUE($B25),'權數表原始_上市114Q4'!$A:$A,0)),"") | O25: =IFERROR(INDEX('權數表原始_上市114Q4'!$CF:$CF,MATCH(VALUE($B25),'權數表原始_上市114Q4'!$A:$A,0)),"") | P25: =N25+O25 | Q25: =P25-IFERROR(INDEX('權數表原始_上市114Q4'!$CG:$CG,MATCH(VALUE($B25),'權數表原始_上市114Q4'!$A:$A,0)),"") | R25: 財務比率不佳(60)；董事長質權設定達其實際持有股數五O%(25)；更換會計師（非屬會計師事務所內部調整(20)；背書保證(15)；營業收入、營業利益或稅前純益變動較大(13)；每股淨值偏低(10)；董事、監察人質權設定達全體董監實際持(5)
A26: 上市 | B26: 6141 | C26: 柏承 | D26: 黃冠達 | E26: 李齊良 | F26: 台北市大安區基隆路二段112號12樓 | G26: 正風聯合會計師事務所 | H26: 林啟平 | I26: 彭莉真 | J26: -4.65 | K26: 5.88 | L26: 無保留意見(強調事項或其他事項)-前期由其他會計師查核、其他 | M26: 114/03/31 | N26: =IFERROR(INDEX('權數表原始_上市114Q4'!$BN:$BN,MATCH(VALUE($B26),'權數表原始_上市114Q4'!$A:$A,0)),"") | O26: =IFERROR(INDEX('權數表原始_上市114Q4'!$CF:$CF,MATCH(VALUE($B26),'權數表原始_上市114Q4'!$A:$A,0)),"") | P26: =N26+O26 | Q26: =P26-IFERROR(INDEX('權數表原始_上市114Q4'!$CG:$CG,MATCH(VALUE($B26),'權數表原始_上市114Q4'!$A:$A,0)),"") | R26: 財務比率不佳(35)；資金貸於他人(27)；會計主管辭職(20)；營業收入、營業利益或稅前純益變動較大(15)；背書保證(15)；董事長質權設定達其實際持有股數五O%(15)；每股淨值偏低(10)；董事、監察人質權設定達全體董監實際持(10) | S26: 新承接（審計510 期初餘額）
A27: 上市 | B27: 2524 | C27: 京城 | D27: 李佩琳 | E27: 蔡天贊 | F27: 高雄市左營區博愛二路150號16樓 | G27: 信永中和聯合會計師事務所 | H27: 莊淑媛 | I27: 卓傳陣 | J27: 1.71 | K27: 57.45 | L27: 無保留意見(強調事項或其他事項)-採用其他會計師查核(核閱)報告且欲區分責任 | M27: 115/03/12 | N27: =IFERROR(INDEX('權數表原始_上市114Q4'!$BN:$BN,MATCH(VALUE($B27),'權數表原始_上市114Q4'!$A:$A,0)),"") | O27: =IFERROR(INDEX('權數表原始_上市114Q4'!$CF:$CF,MATCH(VALUE($B27),'權數表原始_上市114Q4'!$A:$A,0)),"") | P27: =N27+O27 | Q27: =P27-IFERROR(INDEX('權數表原始_上市114Q4'!$CG:$CG,MATCH(VALUE($B27),'權數表原始_上市114Q4'!$A:$A,0)),"") | R27: 財務比率不佳(55)；總經理質權設定達其實際持有股數五O%(25)；營業收入、營業利益或稅前純益變動較大(22)；董事、監察人質權設定達全體董監實際持(20)；董事長質權設定達其實際持有股數五O%(20)；關係企業之交易(4)
A28: 上櫃 | B28: 4113 | C28: 聯上 | D28: 廖昭慈 | E28: 蘇永義 | F28: 高雄市左營區富國路185號17樓之2 | G28: 廣信益群聯合會計師事務所 | H28: 梁宏瑋 | I28: 翁子霖 | J28: -0.43 | K28: 18.46 | L28: 無保留意見 | M28: 115/03/12 | N28: =IFERROR(INDEX('權數表原始_上櫃114Q4'!$BN:$BN,MATCH(VALUE($B28),'權數表原始_上櫃114Q4'!$A:$A,0)),"") | O28: =IFERROR(INDEX('權數表原始_上櫃114Q4'!$CF:$CF,MATCH(VALUE($B28),'權數表原始_上櫃114Q4'!$A:$A,0)),"") | P28: =N28+O28 | Q28: =P28-IFERROR(INDEX('權數表原始_上櫃114Q4'!$CG:$CG,MATCH(VALUE($B28),'權數表原始_上櫃114Q4'!$A:$A,0)),"") | R28: 財務比率不佳(80)；營業收入、營業利益或稅前純益變動較大(27)；採用權益法之關聯企業及合資損益份額((20)；董事、監察人質權設定達全體董監實際持(5)；董事長質權設定達其實際持有股數五O%(5)；總經理質權設定達其實際持有股數五O%(5)；關係企業之交易(3)
A29: 上市 | B29: 2545 | C29: 皇翔 | D29: 黃靖雅 | E29: 廖年吉 | F29: 台北市博愛路38號8樓 | G29: 安侯建業聯合會計師事務所 | H29: 鄒依芸 | I29: 陳宗哲 | J29: 1.92 | K29: 39.34 | L29: 無保留意見 | M29: 115/03/12 | N29: =IFERROR(INDEX('權數表原始_上市114Q4'!$BN:$BN,MATCH(VALUE($B29),'權數表原始_上市114Q4'!$A:$A,0)),"") | O29: =IFERROR(INDEX('權數表原始_上市114Q4'!$CF:$CF,MATCH(VALUE($B29),'權數表原始_上市114Q4'!$A:$A,0)),"") | P29: =N29+O29 | Q29: =P29-IFERROR(INDEX('權數表原始_上市114Q4'!$CG:$CG,MATCH(VALUE($B29),'權數表原始_上市114Q4'!$A:$A,0)),"") | R29: 財務比率不佳(85)；營業收入、營業利益或稅前純益變動較大(21)；總經理質權設定達其實際持有股數五O%(20)；關係企業之交易(18)
A30: 上市 | B30: 6952 | C30: 大武山 | D30: 彭嘉衛 | E30: 林鳳春 | F30: 屏東縣新埤鄉萬隆村平山路68-30號 | G30: 資誠聯合會計師事務所 | H30: 廖阿甚 | I30: 吳建志 | J30: -1.08 | K30: 21.21 | L30: 無保留意見(強調事項或其他事項)-前期由其他會計師查核、其他、欲強調某一事項-具重大影響之災害 | M30: 115/03/06 | N30: =IFERROR(INDEX('權數表原始_上市114Q4'!$BN:$BN,MATCH(VALUE($B30),'權數表原始_上市114Q4'!$A:$A,0)),"") | O30: =IFERROR(INDEX('權數表原始_上市114Q4'!$CF:$CF,MATCH(VALUE($B30),'權數表原始_上市114Q4'!$A:$A,0)),"") | P30: =N30+O30 | Q30: =P30-IFERROR(INDEX('權數表原始_上市114Q4'!$CG:$CG,MATCH(VALUE($B30),'權數表原始_上市114Q4'!$A:$A,0)),"") | R30: 財務比率不佳(70)；關係企業之交易(27)；營業收入、營業利益或稅前純益變動較大(22)；董監事持股異動(15)；獨立董事辭職(10) | S30: 新承接（審計510 期初餘額）
A31: 上櫃 | B31: 4123 | C31: 晟德 | D31: 劉瓊遙 | E31: 王素琦 | F31: 台北市南港區園區街3之2號7樓 | G31: 富鋒聯合會計師事務所 | H31: 鄭忠昊 | I31: 紀嘉祐 | J31: 12.33 | K31: 35.48 | L31: 無保留意見(強調事項或其他事項)-採用其他會計師查核(核閱)報告且欲區分責任 | M31: 115/03/03 | N31: =IFERROR(INDEX('權數表原始_上櫃114Q4'!$BN:$BN,MATCH(VALUE($B31),'權數表原始_上櫃114Q4'!$A:$A,0)),"") | O31: =IFERROR(INDEX('權數表原始_上櫃114Q4'!$CF:$CF,MATCH(VALUE($B31),'權數表原始_上櫃114Q4'!$A:$A,0)),"") | P31: =N31+O31 | Q31: =P31-IFERROR(INDEX('權數表原始_上櫃114Q4'!$CG:$CG,MATCH(VALUE($B31),'權數表原始_上櫃114Q4'!$A:$A,0)),"") | R31: 財務比率不佳(35)；非流動之股權投資占權益比重較高(30)；當期非流動之股權投資增減金額占權益比(30)；採用權益法之關聯企業及合資損益份額((25)；營業收入、營業利益或稅前純益變動較大(22)
A32: 上櫃 | B32: 8927 | C32: 北基 | D32: 廖昭慈 | E32: 鍾育霖 | F32: 新北市板橋區新海路137號 | G32: 安侯建業聯合會計師事務所 | H32: 羅瑞芝 | I32: 余聖河 | J32: 0.35 | K32: 13.28 | L32: 無保留意見(強調事項或其他事項)-其他、欲強調某一事項-重大訴訟或監管措施未來結果之不確定性 | M32: 115/03/31 | N32: =IFERROR(INDEX('權數表原始_上櫃114Q4'!$BN:$BN,MATCH(VALUE($B32),'權數表原始_上櫃114Q4'!$A:$A,0)),"") | O32: =IFERROR(INDEX('權數表原始_上櫃114Q4'!$CF:$CF,MATCH(VALUE($B32),'權數表原始_上櫃114Q4'!$A:$A,0)),"") | P32: =N32+O32 | Q32: =P32-IFERROR(INDEX('權數表原始_上櫃114Q4'!$CG:$CG,MATCH(VALUE($B32),'權數表原始_上櫃114Q4'!$A:$A,0)),"") | R32: 財務比率不佳(75)；營業收入、營業利益或稅前純益變動較大(17)；背書保證(15)；內稽主管辭職(10)；董事長辭職(10)；董事長質權設定達其實際持有股數五O%(10)；董事、監察人質權設定達全體董監實際持(5)
A33: 上市 | B33: 1418 | C33: 東華 | D33: 曾冠程 | E33: 林壯儒 | F33: 台北市新生南路1段56號9樓 | G33: 正風聯合會計師事務所 | H33: 吳欣亮 | I33: 賴家裕 | J33: -1.29 | K33: 22.68 | L33: 無保留意見(強調事項或其他事項)-其他 | M33: 115/03/05 | N33: =IFERROR(INDEX('權數表原始_上市114Q4'!$BN:$BN,MATCH(VALUE($B33),'權數表原始_上市114Q4'!$A:$A,0)),"") | O33: =IFERROR(INDEX('權數表原始_上市114Q4'!$CF:$CF,MATCH(VALUE($B33),'權數表原始_上市114Q4'!$A:$A,0)),"") | P33: =N33+O33 | Q33: =P33-IFERROR(INDEX('權數表原始_上市114Q4'!$CG:$CG,MATCH(VALUE($B33),'權數表原始_上市114Q4'!$A:$A,0)),"") | R33: 財務比率不佳(100)；營業收入、營業利益或稅前純益變動較大(24)；背書保證(15)
A34: 上市 | B34: 2104 | C34: 國際中橡 | D34: 靜平代光遙 | E34: 辜公怡 | F34: 台北市中山北路二段113號8樓 | G34: 勤業眾信聯合會計師事務所 | H34: 龔則立 | I34: 黃秀椿 | J34: -4.28 | K34: 24.88 | L34: 無保留意見 | M34: 115/03/10 | N34: =IFERROR(INDEX('權數表原始_上市114Q4'!$BN:$BN,MATCH(VALUE($B34),'權數表原始_上市114Q4'!$A:$A,0)),"") | O34: =IFERROR(INDEX('權數表原始_上市114Q4'!$CF:$CF,MATCH(VALUE($B34),'權數表原始_上市114Q4'!$A:$A,0)),"") | P34: =N34+O34 | Q34: =P34-IFERROR(INDEX('權數表原始_上市114Q4'!$CG:$CG,MATCH(VALUE($B34),'權數表原始_上市114Q4'!$A:$A,0)),"") | R34: 採用權益法之關聯企業及合資損益份額((50)；營業收入、營業利益或稅前純益變動較大(24)；資金貸於他人(20)；財務比率不佳(20)；背書保證(15)；非流動之股權投資占權益比重較高(10)
A35: 上市 | B35: 2537 | C35: 聯上發 | D35: 廖昭慈 | E35: 蘇永義 | F35: 台北市信義區忠孝東路五段68號36樓 | G35: 安侯建業聯合會計師事務所 | H35: 黃欣婷 | I35: 鄒依芸 | J35: 0.15 | K35: 14.75 | L35: 無保留意見(強調事項或其他事項)-採用其他會計師查核(核閱)報告且欲區分責任 | M35: 115/03/11 | N35: =IFERROR(INDEX('權數表原始_上市114Q4'!$BN:$BN,MATCH(VALUE($B35),'權數表原始_上市114Q4'!$A:$A,0)),"") | O35: =IFERROR(INDEX('權數表原始_上市114Q4'!$CF:$CF,MATCH(VALUE($B35),'權數表原始_上市114Q4'!$A:$A,0)),"") | P35: =N35+O35 | Q35: =P35-IFERROR(INDEX('權數表原始_上市114Q4'!$CG:$CG,MATCH(VALUE($B35),'權數表原始_上市114Q4'!$A:$A,0)),"") | R35: 財務比率不佳(80)；總經理質權設定達其實際持有股數五O%(25)；營業收入、營業利益或稅前純益變動較大(21)；董事、監察人質權設定達全體董監實際持(5)；董事長質權設定達其實際持有股數五O%(5)；關係企業之交易(3)
A36: 上櫃 | B36: 8068 | C36: 全達 | D36: 許瀚文 | E36: 凃俊榮 | F36: 臺北市內湖區內湖路一段360巷15號8樓之1 | G36: 安侯建業聯合會計師事務所 | H36: 余聖河 | I36: 羅瑞芝 | J36: 1.23 | K36: 13.99 | L36: 無保留意見(強調事項或其他事項)-採用其他會計師查核(核閱)報告且欲區分責任 | M36: 115/03/30 | N36: =IFERROR(INDEX('權數表原始_上櫃114Q4'!$BN:$BN,MATCH(VALUE($B36),'權數表原始_上櫃114Q4'!$A:$A,0)),"") | O36: =IFERROR(INDEX('權數表原始_上櫃114Q4'!$CF:$CF,MATCH(VALUE($B36),'權數表原始_上櫃114Q4'!$A:$A,0)),"") | P36: =N36+O36 | Q36: =P36-IFERROR(INDEX('權數表原始_上櫃114Q4'!$CG:$CG,MATCH(VALUE($B36),'權數表原始_上櫃114Q4'!$A:$A,0)),"") | R36: 財務比率不佳(45)；非流動之股權投資占權益比重較高(30)；當期非流動之股權投資增減金額占權益比(30)；關係企業之交易(25)；營業收入、營業利益或稅前純益變動較大(9)
A37: 上櫃 | B37: 6134 | C37: 萬旭 | D37: 林抒真 | E37: 張程欽 | F37: 新北市五股區工業區五工六路72號3樓 | G37: 資誠聯合會計師事務所 | H37: 林柏全 | I37: 王菘澤 | J37: 0.12 | K37: 12.31 | L37: 無保留意見(強調事項或其他事項)-採用其他會計師查核(核閱)報告且欲區分責任 | M37: 115/03/09 | N37: =IFERROR(INDEX('權數表原始_上櫃114Q4'!$BN:$BN,MATCH(VALUE($B37),'權數表原始_上櫃114Q4'!$A:$A,0)),"") | O37: =IFERROR(INDEX('權數表原始_上櫃114Q4'!$CF:$CF,MATCH(VALUE($B37),'權數表原始_上櫃114Q4'!$A:$A,0)),"") | P37: =N37+O37 | Q37: =P37-IFERROR(INDEX('權數表原始_上櫃114Q4'!$CG:$CG,MATCH(VALUE($B37),'權數表原始_上櫃114Q4'!$A:$A,0)),"") | R37: 財務比率不佳(50)；採用權益法之關聯企業及合資損益份額((40)；關係企業之交易(15)；營業收入、營業利益或稅前純益變動較大(13)；非流動之股權投資占權益比重較高(10)；內稽主管辭職(10)
A38: 上市 | B38: 2101 | C38: 南港 | D38: 怡秀代光遙代殷若瑛 | E38: 郭林諒 | F38: 台北市大安區仁愛路三段136號6樓608室 | G38: 正風聯合會計師事務所 | H38: 彭莉真 | I38: 林啟平 | J38: 1.01 | K38: 17.4 | L38: 無保留意見 | M38: 115/03/11 | N38: =IFERROR(INDEX('權數表原始_上市114Q4'!$BN:$BN,MATCH(VALUE($B38),'權數表原始_上市114Q4'!$A:$A,0)),"") | O38: =IFERROR(INDEX('權數表原始_上市114Q4'!$CF:$CF,MATCH(VALUE($B38),'權數表原始_上市114Q4'!$A:$A,0)),"") | P38: =N38+O38 | Q38: =P38-IFERROR(INDEX('權數表原始_上市114Q4'!$CG:$CG,MATCH(VALUE($B38),'權數表原始_上市114Q4'!$A:$A,0)),"") | R38: 財務比率不佳(55)；營業收入、營業利益或稅前純益變動較大(20)；非流動之股權投資占權益比重較高(20)；資金貸於他人(17)；背書保證(15)；當期非流動之股權投資增減金額占權益比(10)
A39: 上櫃 | B39: 4139 | C39: 馬光-KY | D39: 林抒真 | E39: 福苓興業有限公司代表人:巫雲光 | F39: P.O. Box 61, Harbour Centre, George Town, Grand Cayman | G39: 安永聯合會計師事務所 | H39: 陳政初 | I39: 姚世傑 | J39: -1.55 | K39: 9.82 | L39: 無保留意見 | M39: 115/03/12 | N39: =IFERROR(INDEX('權數表原始_上櫃114Q4'!$BN:$BN,MATCH(VALUE($B39),'權數表原始_上櫃114Q4'!$A:$A,0)),"") | O39: =IFERROR(INDEX('權數表原始_上櫃114Q4'!$CF:$CF,MATCH(VALUE($B39),'權數表原始_上櫃114Q4'!$A:$A,0)),"") | P39: =N39+O39 | Q39: =P39-IFERROR(INDEX('權數表原始_上櫃114Q4'!$CG:$CG,MATCH(VALUE($B39),'權數表原始_上櫃114Q4'!$A:$A,0)),"") | R39: 財務比率不佳(45)；營業收入、營業利益或稅前純益變動較大(22)；資金貸於他人(20)；背書保證(15)；董監事持股異動(15)；非流動之股權投資占權益比重較高(10)；每股淨值偏低(5)；董事辭職(5) | S39: KY
A40: 上櫃 | B40: 6180 | C40: 橘子 | D40: 李靜平 | E40: 劉柏園 | F40: 台北市內湖區瑞湖街111號 | G40: 資誠聯合會計師事務所 | H40: 顏裕芳 | I40: 林永智 | J40: -1.53 | K40: 24.37 | L40: 無保留意見(強調事項或其他事項)-採用其他會計師查核(核閱)報告且欲區分責任 | M40: 115/03/02 | N40: =IFERROR(INDEX('權數表原始_上櫃114Q4'!$BN:$BN,MATCH(VALUE($B40),'權數表原始_上櫃114Q4'!$A:$A,0)),"") | O40: =IFERROR(INDEX('權數表原始_上櫃114Q4'!$CF:$CF,MATCH(VALUE($B40),'權數表原始_上櫃114Q4'!$A:$A,0)),"") | P40: =N40+O40 | Q40: =P40-IFERROR(INDEX('權數表原始_上櫃114Q4'!$CG:$CG,MATCH(VALUE($B40),'權數表原始_上櫃114Q4'!$A:$A,0)),"") | R40: 財務比率不佳(60)；營業收入、營業利益或稅前純益變動較大(22)；董事長質權設定達其實際持有股數五O%(20)；總經理質權設定達其實際持有股數五O%(20)；非流動之股權投資占權益比重較高(10)；董事、監察人質權設定達全體董監實際持(5)
A41: 上市 | B41: 6873 | C41: 泓德能源 | D41: 怡秀代若瑛 | E41: 謝源一 | F41: 臺北市士林區德行西路35號5樓 | G41: 安侯建業聯合會計師事務所 | H41: 吳俊源 | I41: 黃海寧 | J41: 3.59 | K41: 73.02 | L41: 無保留意見 | M41: 115/03/10 | N41: =IFERROR(INDEX('權數表原始_上市114Q4'!$BN:$BN,MATCH(VALUE($B41),'權數表原始_上市114Q4'!$A:$A,0)),"") | O41: =IFERROR(INDEX('權數表原始_上市114Q4'!$CF:$CF,MATCH(VALUE($B41),'權數表原始_上市114Q4'!$A:$A,0)),"") | P41: =N41+O41 | Q41: =P41-IFERROR(INDEX('權數表原始_上市114Q4'!$CG:$CG,MATCH(VALUE($B41),'權數表原始_上市114Q4'!$A:$A,0)),"") | R41: 財務比率不佳(60)；關係企業之交易(37)；背書保證(15)；營業收入、營業利益或稅前純益變動較大(13)；資金貸於他人(7)；總經理質權設定達其實際持有股數五O%(5)
A42: 上市 | B42: 2461 | C42: 光群雷 | D42: 瓊遙代若瑛 | E42: 郭維武 | F42: 新竹市科學工業園區力行六路一號 | G42: 勤業眾信聯合會計師事務所 | H42: 吳恪昌 | I42: 徐文亞 | J42: -0.61 | K42: 17.52 | L42: 無保留意見(強調事項或其他事項)-採用其他會計師查核(核閱)報告且欲區分責任 | M42: 115/03/20 | N42: =IFERROR(INDEX('權數表原始_上市114Q4'!$BN:$BN,MATCH(VALUE($B42),'權數表原始_上市114Q4'!$A:$A,0)),"") | O42: =IFERROR(INDEX('權數表原始_上市114Q4'!$CF:$CF,MATCH(VALUE($B42),'權數表原始_上市114Q4'!$A:$A,0)),"") | P42: =N42+O42 | Q42: =P42-IFERROR(INDEX('權數表原始_上市114Q4'!$CG:$CG,MATCH(VALUE($B42),'權數表原始_上市114Q4'!$A:$A,0)),"") | R42: 財務比率不佳(40)；採用權益法之關聯企業及合資損益份額((30)；營業收入、營業利益或稅前純益變動較大(21)；董事、監察人質權設定達全體董監實際持(15)；董事長質權設定達其實際持有股數五O%(15)；總經理質權設定達其實際持有股數五O%(15)
A43: 上櫃 | B43: 3664 | C43: 安瑞-KY | D43: 申宛云 | E43: 連建欽 | F43: North Sound Rd., George Town, Grand Cayman, KY1-9006 | G43: 安永聯合會計師事務所 | H43: 王瑄瑄 | I43: 林秀青 | J43: -6.02 | K43: 1.4 | L43: 無保留意見(強調事項或其他事項)-前期由其他會計師查核、其他 | M43: 115/03/31 | N43: =IFERROR(INDEX('權數表原始_上櫃114Q4'!$BN:$BN,MATCH(VALUE($B43),'權數表原始_上櫃114Q4'!$A:$A,0)),"") | O43: =IFERROR(INDEX('權數表原始_上櫃114Q4'!$CF:$CF,MATCH(VALUE($B43),'權數表原始_上櫃114Q4'!$A:$A,0)),"") | P43: =N43+O43 | Q43: =P43-IFERROR(INDEX('權數表原始_上櫃114Q4'!$CG:$CG,MATCH(VALUE($B43),'權數表原始_上櫃114Q4'!$A:$A,0)),"") | R43: 財務比率不佳(55)；資金貸於他人(30)；營業收入、營業利益或稅前純益變動較大(25)；每股淨值偏低(15)；獨立董事辭職(10) | S43: 新承接（審計510 期初餘額）；KY
A44: 上市 | B44: 2314 | C44: 台揚 | D44: 趙彥銨 | E44: 謝其嘉 | F44: 新竹科學園區新竹市創新二路一號 | G44: 資誠聯合會計師事務所 | H44: 劉倩瑜 | I44: 鄭雅慧 | J44: -6.11 | K44: 1.28 | L44: 無保留意見(繼續經營有關之重大不確定性)-繼續經營能力存在重大不確定性/繼續經營假設存有重大疑慮 | M44: 115/03/11 | N44: =IFERROR(INDEX('權數表原始_上市114Q4'!$BN:$BN,MATCH(VALUE($B44),'權數表原始_上市114Q4'!$A:$A,0)),"") | O44: =IFERROR(INDEX('權數表原始_上市114Q4'!$CF:$CF,MATCH(VALUE($B44),'權數表原始_上市114Q4'!$A:$A,0)),"") | P44: =N44+O44 | Q44: =P44-IFERROR(INDEX('權數表原始_上市114Q4'!$CG:$CG,MATCH(VALUE($B44),'權數表原始_上市114Q4'!$A:$A,0)),"") | R44: 財務比率不佳(70)；非流動之股權投資占權益比重較高(30)；每股淨值偏低(15)；內稽主管辭職(10)；營業收入、營業利益或稅前純益變動較大(9)
A45: 上櫃 | B45: 5701 | C45: 劍湖山 | D45: 黃靖雅 | E45: 尤義賢 | F45: 雲林縣古坑鄉永光村大湖口六十七號 | G45: 國富浩華聯合會計師事務所 | H45: 黃鈴雯 | I45: 李國銘 | J45: -0.26 | K45: 3.7 | L45: 無保留意見 | M45: 115/03/11 | N45: =IFERROR(INDEX('權數表原始_上櫃114Q4'!$BN:$BN,MATCH(VALUE($B45),'權數表原始_上櫃114Q4'!$A:$A,0)),"") | O45: =IFERROR(INDEX('權數表原始_上櫃114Q4'!$CF:$CF,MATCH(VALUE($B45),'權數表原始_上櫃114Q4'!$A:$A,0)),"") | P45: =N45+O45 | Q45: =P45-IFERROR(INDEX('權數表原始_上櫃114Q4'!$CG:$CG,MATCH(VALUE($B45),'權數表原始_上櫃114Q4'!$A:$A,0)),"") | R45: 財務比率不佳(45)；非流動之股權投資占權益比重較高(30)；財務主管辭職(20)；每股淨值偏低(15)；營業收入、營業利益或稅前純益變動較大(14)；總經理辭職(10)
A46: 上市 | B46: 6165 | C46: 浪凡 | D46: 黃冠達 | E46: 王亦衡 | F46: 臺北市士林區中山北路五段506號4樓 | G46: 安侯建業聯合會計師事務所 | H46: 紀孟君 | I46: 楊樹芝 | J46: 4.02 | K46: 20.91 | L46: 無保留意見 | M46: 115/03/12 | N46: =IFERROR(INDEX('權數表原始_上市114Q4'!$BN:$BN,MATCH(VALUE($B46),'權數表原始_上市114Q4'!$A:$A,0)),"") | O46: =IFERROR(INDEX('權數表原始_上市114Q4'!$CF:$CF,MATCH(VALUE($B46),'權數表原始_上市114Q4'!$A:$A,0)),"") | P46: =N46+O46 | Q46: =P46-IFERROR(INDEX('權數表原始_上市114Q4'!$CG:$CG,MATCH(VALUE($B46),'權數表原始_上市114Q4'!$A:$A,0)),"") | R46: 財務比率不佳(35)；董事、監察人質權設定達全體董監實際持(25)；董事長質權設定達其實際持有股數五O%(25)；總經理質權設定達其實際持有股數五O%(25)；營業收入、營業利益或稅前純益變動較大(24)
A47: 上櫃 | B47: 3713 | C47: 新晶投控 | D47: 許瀚文 | E47: 資三德 | F47: 新竹縣竹北市復興二路193號3樓之一 | G47: 安侯建業聯合會計師事務所 | H47: 楊樹芝 | I47: 陳蓓琪 | J47: -1.13 | K47: 8.03 | L47: 無保留意見 | M47: 115/03/12 | N47: =IFERROR(INDEX('權數表原始_上櫃114Q4'!$BN:$BN,MATCH(VALUE($B47),'權數表原始_上櫃114Q4'!$A:$A,0)),"") | O47: =IFERROR(INDEX('權數表原始_上櫃114Q4'!$CF:$CF,MATCH(VALUE($B47),'權數表原始_上櫃114Q4'!$A:$A,0)),"") | P47: =N47+O47 | Q47: =P47-IFERROR(INDEX('權數表原始_上櫃114Q4'!$CG:$CG,MATCH(VALUE($B47),'權數表原始_上櫃114Q4'!$A:$A,0)),"") | R47: 財務比率不佳(65)；會計主管辭職(20)；營業收入、營業利益或稅前純益變動較大(18)；背書保證(15)；關係企業之交易(5)；每股淨值偏低(5)；董監事持股異動(5)
A48: 上櫃 | B48: 8431 | C48: 匯鑽科 | D48: 宛云代若瑛 | E48: 花鐳哲 | F48: 台北市內湖區新湖一路151號7樓 | G48: 勤業眾信聯合會計師事務所 | H48: 梁盛泰 | I48: 尤盟貴 | J48: -3.88 | K48: 16.32 | L48: 無保留意見(強調事項或其他事項)-採用其他會計師查核(核閱)報告且欲區分責任 | M48: 115/03/31 | N48: =IFERROR(INDEX('權數表原始_上櫃114Q4'!$BN:$BN,MATCH(VALUE($B48),'權數表原始_上櫃114Q4'!$A:$A,0)),"") | O48: =IFERROR(INDEX('權數表原始_上櫃114Q4'!$CF:$CF,MATCH(VALUE($B48),'權數表原始_上櫃114Q4'!$A:$A,0)),"") | P48: =N48+O48 | Q48: =P48-IFERROR(INDEX('權數表原始_上櫃114Q4'!$CG:$CG,MATCH(VALUE($B48),'權數表原始_上櫃114Q4'!$A:$A,0)),"") | R48: 資金貸於他人(35)；財務比率不佳(35)；營業收入、營業利益或稅前純益變動較大(22)；董監事持股異動(15)；內稽主管辭職(10)；總經理辭職(10)；董事辭職(5)
A49: 上市 | B49: 1598 | C49: 岱宇 | D49: 馨云代伯強代林育安 | E49: 林佑穎 | F49: (104)台北市中山區松江路111號12樓 | G49: 安侯建業聯合會計師事務所 | H49: 陳宗哲 | I49: 鄒依芸 | J49: -3.35 | K49: 24.84 | L49: 無保留意見 | M49: 115/03/27 | N49: =IFERROR(INDEX('權數表原始_上市114Q4'!$BN:$BN,MATCH(VALUE($B49),'權數表原始_上市114Q4'!$A:$A,0)),"") | O49: =IFERROR(INDEX('權數表原始_上市114Q4'!$CF:$CF,MATCH(VALUE($B49),'權數表原始_上市114Q4'!$A:$A,0)),"") | P49: =N49+O49 | Q49: =P49-IFERROR(INDEX('權數表原始_上市114Q4'!$CG:$CG,MATCH(VALUE($B49),'權數表原始_上市114Q4'!$A:$A,0)),"") | R49: 財務比率不佳(45)；營業收入、營業利益或稅前純益變動較大(24)；資金貸於他人(20)；董事、監察人質權設定達全體董監實際持(20)；董事長質權設定達其實際持有股數五O%(20)
A50: 上市 | B50: 4426 | C50: 利勤 | D50: 抒真代光遙 | E50: 洪文耀 | F50: 雲林縣斗六市斗工十二路5號 | G50: 安侯建業聯合會計師事務所 | H50: 陳政學 | I50: 張字信 | J50: -2.94 | K50: 10.85 | L50: 無保留意見 | M50: 115/03/12 | N50: =IFERROR(INDEX('權數表原始_上市114Q4'!$BN:$BN,MATCH(VALUE($B50),'權數表原始_上市114Q4'!$A:$A,0)),"") | O50: =IFERROR(INDEX('權數表原始_上市114Q4'!$CF:$CF,MATCH(VALUE($B50),'權數表原始_上市114Q4'!$A:$A,0)),"") | P50: =N50+O50 | Q50: =P50-IFERROR(INDEX('權數表原始_上市114Q4'!$CG:$CG,MATCH(VALUE($B50),'權數表原始_上市114Q4'!$A:$A,0)),"") | R50: 財務比率不佳(50)；資金貸於他人(20)；財務主管辭職(20)；會計主管辭職(20)；營業收入、營業利益或稅前純益變動較大(18)
A51: 上市 | B51: 2538 | C51: 基泰 | D51: 詹孟真 | E51: 楊儲明 | F51: 台北市中正區衡陽路五十一號十樓 | G51: 安永聯合會計師事務所 | H51: 林素雯 | I51: 張巧穎 | J51: 0.35 | K51: 12.85 | L51: 無保留意見(強調事項或其他事項)-採用其他會計師查核(核閱)報告且欲區分責任、其他 | M51: 115/03/11 | N51: =IFERROR(INDEX('權數表原始_上市114Q4'!$BN:$BN,MATCH(VALUE($B51),'權數表原始_上市114Q4'!$A:$A,0)),"") | O51: =IFERROR(INDEX('權數表原始_上市114Q4'!$CF:$CF,MATCH(VALUE($B51),'權數表原始_上市114Q4'!$A:$A,0)),"") | P51: =N51+O51 | Q51: =P51-IFERROR(INDEX('權數表原始_上市114Q4'!$CG:$CG,MATCH(VALUE($B51),'權數表原始_上市114Q4'!$A:$A,0)),"") | R51: 財務比率不佳(60)；採用權益法之關聯企業及合資損益份額((40)；營業收入、營業利益或稅前純益變動較大(17)；背書保證(10)
A52: 上市 | B52: 2611 | C52: 志信 | D52: 怡秀代伯強 | E52: 黃春發 | F52: 台北市大安區市民大道三段206號6樓 | G52: 勤業眾信聯合會計師事務所 | H52: 方涵妮 | I52: 陳昭宇 | J52: 0.52 | K52: 14.36 | L52: 無保留意見 | M52: 115/03/11 | N52: =IFERROR(INDEX('權數表原始_上市114Q4'!$BN:$BN,MATCH(VALUE($B52),'權數表原始_上市114Q4'!$A:$A,0)),"") | O52: =IFERROR(INDEX('權數表原始_上市114Q4'!$CF:$CF,MATCH(VALUE($B52),'權數表原始_上市114Q4'!$A:$A,0)),"") | P52: =N52+O52 | Q52: =P52-IFERROR(INDEX('權數表原始_上市114Q4'!$CG:$CG,MATCH(VALUE($B52),'權數表原始_上市114Q4'!$A:$A,0)),"") | R52: 財務比率不佳(40)；關係企業之交易(27)；董事長質權設定達其實際持有股數五O%(25)；最近一年內有訴訟事件對公司財務業務有(20)；營業收入、營業利益或稅前純益變動較大(15)
A53: 上櫃 | B53: 6111 | C53: 光聚晶電 | D53: 張怡真 | E53: 凃俊光 | F53: 台北市大安區敦化南路2段11巷8號7樓 | G53: 安永聯合會計師事務所 | H53: 呂倩雯 | I53: 王慕凡 | J53: -4.63 | K53: 18.33 | L53: 無保留意見(強調事項或其他事項)-採用其他會計師查核(核閱)報告且欲區分責任 | M53: 115/03/31 | N53: =IFERROR(INDEX('權數表原始_上櫃114Q4'!$BN:$BN,MATCH(VALUE($B53),'權數表原始_上櫃114Q4'!$A:$A,0)),"") | O53: =IFERROR(INDEX('權數表原始_上櫃114Q4'!$CF:$CF,MATCH(VALUE($B53),'權數表原始_上櫃114Q4'!$A:$A,0)),"") | P53: =N53+O53 | Q53: =P53-IFERROR(INDEX('權數表原始_上櫃114Q4'!$CG:$CG,MATCH(VALUE($B53),'權數表原始_上櫃114Q4'!$A:$A,0)),"") | R53: 財務比率不佳(80)；營業收入、營業利益或稅前純益變動較大(27)；資金貸於他人(10)；背書保證(5)；董事、監察人質權設定達全體董監實際持(5)
A54: 上櫃 | B54: 4127 | C54: 天良 | D54: 邱棕晉 | E54: 詹漢山 | F54: 新北市汐止區大同路一段147號9樓 | G54: 正風聯合會計師事務所 | H54: 賴家裕 | I54: 賴永吉 | J54: -0.22 | K54: 10.36 | L54: 無保留意見 | M54: 115/03/11 | N54: =IFERROR(INDEX('權數表原始_上櫃114Q4'!$BN:$BN,MATCH(VALUE($B54),'權數表原始_上櫃114Q4'!$A:$A,0)),"") | O54: =IFERROR(INDEX('權數表原始_上櫃114Q4'!$CF:$CF,MATCH(VALUE($B54),'權數表原始_上櫃114Q4'!$A:$A,0)),"") | P54: =N54+O54 | Q54: =P54-IFERROR(INDEX('權數表原始_上櫃114Q4'!$CG:$CG,MATCH(VALUE($B54),'權數表原始_上櫃114Q4'!$A:$A,0)),"") | R54: 財務比率不佳(70)；營業收入、營業利益或稅前純益變動較大(26)；財務主管辭職(20)；非流動之股權投資占權益比重較高(10)
A55: 上櫃 | B55: 5213 | C55: 亞昕 | D55: 許瀚文 | E55: 姚政岳 | F55: 新北市新莊區思源路555號30樓 | G55: 安侯建業聯合會計師事務所 | H55: 潘俊名 | I55: 陳宗哲 | J55: 3.06 | K55: 22.5 | L55: 無保留意見 | M55: 115/03/04 | N55: =IFERROR(INDEX('權數表原始_上櫃114Q4'!$BN:$BN,MATCH(VALUE($B55),'權數表原始_上櫃114Q4'!$A:$A,0)),"") | O55: =IFERROR(INDEX('權數表原始_上櫃114Q4'!$CF:$CF,MATCH(VALUE($B55),'權數表原始_上櫃114Q4'!$A:$A,0)),"") | P55: =N55+O55 | Q55: =P55-IFERROR(INDEX('權數表原始_上櫃114Q4'!$CG:$CG,MATCH(VALUE($B55),'權數表原始_上櫃114Q4'!$A:$A,0)),"") | R55: 財務比率不佳(50)；營業收入、營業利益或稅前純益變動較大(28)；總經理質權設定達其實際持有股數五O%(25)；董事長質權設定達其實際持有股數五O%(15)；董事、監察人質權設定達全體董監實際持(5)；關係企業之交易(3)
A56: 上櫃 | B56: 6441 | C56: 廣錠 | D56: 李佩琳 | E56: 廖良彬 | F56: 新北市汐止區新台五路一段93號24樓 | G56: 安侯建業聯合會計師事務所 | H56: 潘俊名 | I56: 張淑瑩 | J56: -5.16 | K56: 19.17 | L56: 無保留意見 | M56: 115/02/24 | N56: =IFERROR(INDEX('權數表原始_上櫃114Q4'!$BN:$BN,MATCH(VALUE($B56),'權數表原始_上櫃114Q4'!$A:$A,0)),"") | O56: =IFERROR(INDEX('權數表原始_上櫃114Q4'!$CF:$CF,MATCH(VALUE($B56),'權數表原始_上櫃114Q4'!$A:$A,0)),"") | P56: =N56+O56 | Q56: =P56-IFERROR(INDEX('權數表原始_上櫃114Q4'!$CG:$CG,MATCH(VALUE($B56),'權數表原始_上櫃114Q4'!$A:$A,0)),"") | R56: 財務比率不佳(50)；營業收入、營業利益或稅前純益變動較大(21)；董事長質權設定達其實際持有股數五O%(20)；總經理質權設定達其實際持有股數五O%(20)；獨立董事辭職(10)；董事辭職(5)
A57: 上市 | B57: 3312 | C57: 弘憶股 | D57: 林抒真 | E57: 葉佳紋 | F57: 台北市內湖區行忠路57號2樓 | G57: 安侯建業聯合會計師事務所 | H57: 紀孟君 | I57: 楊樹芝 | J57: 1.74 | K57: 21.4 | L57: 無保留意見(強調事項或其他事項)-採用其他會計師查核(核閱)報告且欲區分責任 | M57: 115/03/09 | N57: =IFERROR(INDEX('權數表原始_上市114Q4'!$BN:$BN,MATCH(VALUE($B57),'權數表原始_上市114Q4'!$A:$A,0)),"") | O57: =IFERROR(INDEX('權數表原始_上市114Q4'!$CF:$CF,MATCH(VALUE($B57),'權數表原始_上市114Q4'!$A:$A,0)),"") | P57: =N57+O57 | Q57: =P57-IFERROR(INDEX('權數表原始_上市114Q4'!$CG:$CG,MATCH(VALUE($B57),'權數表原始_上市114Q4'!$A:$A,0)),"") | R57: 關係企業之交易(40)；財務比率不佳(35)；董事、監察人質權設定達全體董監實際持(20)；董事長質權設定達其實際持有股數五O%(20)；營業收入、營業利益或稅前純益變動較大(10)
A58: 上市 | B58: 2338 | C58: 光罩 | D58: 張怡真 | E58: 凃俊光 | F58: 新竹科學園區新竹縣寶山鄉創新一路十一號 | G58: 資誠聯合會計師事務所 | H58: 劉倩瑜 | I58: 蔡欣怡 | J58: -4.88 | K58: 15.45 | L58: 無保留意見(強調事項或其他事項)-其他 | M58: 115/03/13 | N58: =IFERROR(INDEX('權數表原始_上市114Q4'!$BN:$BN,MATCH(VALUE($B58),'權數表原始_上市114Q4'!$A:$A,0)),"") | O58: =IFERROR(INDEX('權數表原始_上市114Q4'!$CF:$CF,MATCH(VALUE($B58),'權數表原始_上市114Q4'!$A:$A,0)),"") | P58: =N58+O58 | Q58: =P58-IFERROR(INDEX('權數表原始_上市114Q4'!$CG:$CG,MATCH(VALUE($B58),'權數表原始_上市114Q4'!$A:$A,0)),"") | R58: 財務比率不佳(40)；營業收入、營業利益或稅前純益變動較大(24)；董事、監察人質權設定達全體董監實際持(15)；董事長質權設定達其實際持有股數五O%(15)；資金貸於他人(10)；董事長辭職(10)；董監事持股異動(5)；總經理質權設定達其實際持有股數五O%(5)
A59: 上櫃 | B59: 2740 | C59: 華軒 | D59: 黃冠達 | E59: 陳銘鴻 | F59: 新北市林口區公園路159號 | G59: 安侯建業聯合會計師事務所 | H59: 黃欣婷 | I59: 池世欽 | J59: -3.19 | K59: 5.61 | L59: 無保留意見 | M59: 115/02/05 | N59: =IFERROR(INDEX('權數表原始_上櫃114Q4'!$BN:$BN,MATCH(VALUE($B59),'權數表原始_上櫃114Q4'!$A:$A,0)),"") | O59: =IFERROR(INDEX('權數表原始_上櫃114Q4'!$CF:$CF,MATCH(VALUE($B59),'權數表原始_上櫃114Q4'!$A:$A,0)),"") | P59: =N59+O59 | Q59: =P59-IFERROR(INDEX('權數表原始_上櫃114Q4'!$CG:$CG,MATCH(VALUE($B59),'權數表原始_上櫃114Q4'!$A:$A,0)),"") | R59: 董事、監察人質權設定達全體董監實際持(25)；董事長質權設定達其實際持有股數五O%(25)；財務比率不佳(20)；營業收入、營業利益或稅前純益變動較大(12)；關係企業之交易(12)；每股淨值偏低(10)；內稽主管辭職(10)；總經理辭職(10)
A60: 上市 | B60: 3092 | C60: 鴻碩 | D60: 陳怡秀 | E60: 張利榮 | F60: 台北市內湖區行愛路169號 | G60: 資誠聯合會計師事務所 | H60: 林雅慧 | I60: 阮呂曼玉 | J60: -5.14 | K60: 13.44 | L60: 無保留意見 | M60: 115/02/26 | N60: =IFERROR(INDEX('權數表原始_上市114Q4'!$BN:$BN,MATCH(VALUE($B60),'權數表原始_上市114Q4'!$A:$A,0)),"") | O60: =IFERROR(INDEX('權數表原始_上市114Q4'!$CF:$CF,MATCH(VALUE($B60),'權數表原始_上市114Q4'!$A:$A,0)),"") | P60: =N60+O60 | Q60: =P60-IFERROR(INDEX('權數表原始_上市114Q4'!$CG:$CG,MATCH(VALUE($B60),'權數表原始_上市114Q4'!$A:$A,0)),"") | R60: 財務比率不佳(50)；資金貸於他人(35)；營業收入、營業利益或稅前純益變動較大(24)；背書保證(15)
A61: 上櫃 | B61: 4907 | C61: 富宇 | D61: 郭秀春 | E61: 張世欣 | F61: 台中市西屯區市政北二路238號16樓之3 | G61: 立本台灣聯合會計師事務所 | H61: 程建憲 | I61: 陶鴻文 | J61: 1.23 | K61: 20.9 | L61: 無保留意見 | M61: 115/03/06 | N61: =IFERROR(INDEX('權數表原始_上櫃114Q4'!$BN:$BN,MATCH(VALUE($B61),'權數表原始_上櫃114Q4'!$A:$A,0)),"") | O61: =IFERROR(INDEX('權數表原始_上櫃114Q4'!$CF:$CF,MATCH(VALUE($B61),'權數表原始_上櫃114Q4'!$A:$A,0)),"") | P61: =N61+O61 | Q61: =P61-IFERROR(INDEX('權數表原始_上櫃114Q4'!$CG:$CG,MATCH(VALUE($B61),'權數表原始_上櫃114Q4'!$A:$A,0)),"") | R61: 財務比率不佳(75)；營業收入、營業利益或稅前純益變動較大(24)；更換會計師（非屬會計師事務所內部調整(20)；關係企業之交易(4)
A62: 上市 | B62: 1512 | C62: 瑞利 | D62: 邱棕晉 | E62: 吳明燦 | F62: 高雄市仁武區高楠公路廿二號 | G62: 資誠聯合會計師事務所 | H62: 王玉娟 | I62: 徐建業 | J62: 0.19 | K62: 6.66 | L62: 無保留意見(強調事項或其他事項)-採用其他會計師查核(核閱)報告且欲區分責任 | M62: 115/03/12 | N62: =IFERROR(INDEX('權數表原始_上市114Q4'!$BN:$BN,MATCH(VALUE($B62),'權數表原始_上市114Q4'!$A:$A,0)),"") | O62: =IFERROR(INDEX('權數表原始_上市114Q4'!$CF:$CF,MATCH(VALUE($B62),'權數表原始_上市114Q4'!$A:$A,0)),"") | P62: =N62+O62 | Q62: =P62-IFERROR(INDEX('權數表原始_上市114Q4'!$CG:$CG,MATCH(VALUE($B62),'權數表原始_上市114Q4'!$A:$A,0)),"") | R62: 財務比率不佳(50)；營業收入、營業利益或稅前純益變動較大(22)；資金貸於他人(20)；背書保證(10)；非流動之股權投資占權益比重較高(10)；每股淨值偏低(10)
A63: 上櫃 | B63: 3710 | C63: 連展投控 | D63: 彭嘉衛 | E63: 林肇聰 | F63: 新北市新店區寶興路45巷9弄2號3樓 | G63: 資誠聯合會計師事務所 | H63: 吳仁杰 | I63: 林永智 | J63: -1.48 | K63: 4.57 | L63: 無保留意見(強調事項或其他事項)-採用其他會計師查核(核閱)報告且欲區分責任 | M63: 115/03/12 | N63: =IFERROR(INDEX('權數表原始_上櫃114Q4'!$BN:$BN,MATCH(VALUE($B63),'權數表原始_上櫃114Q4'!$A:$A,0)),"") | O63: =IFERROR(INDEX('權數表原始_上櫃114Q4'!$CF:$CF,MATCH(VALUE($B63),'權數表原始_上櫃114Q4'!$A:$A,0)),"") | P63: =N63+O63 | Q63: =P63-IFERROR(INDEX('權數表原始_上櫃114Q4'!$CG:$CG,MATCH(VALUE($B63),'權數表原始_上櫃114Q4'!$A:$A,0)),"") | R63: 財務比率不佳(45)；營業收入、營業利益或稅前純益變動較大(22)；資金貸於他人(20)；背書保證(15)；每股淨值偏低(15)；董事辭職(5)
A64: 上櫃 | B64: 5014 | C64: 建錩 | D64: 馨云代伯強 | E64: 李慶柏 | F64: 桃園市大園區田心里大觀路178號 | G64: 資誠聯合會計師事務所 | H64: 吳偉豪 | I64: 鄭雅慧 | J64: -2.37 | K64: 14.43 | L64: 無保留意見(強調事項或其他事項)-採用其他會計師查核(核閱)報告且欲區分責任 | M64: 115/03/13 | N64: =IFERROR(INDEX('權數表原始_上櫃114Q4'!$BN:$BN,MATCH(VALUE($B64),'權數表原始_上櫃114Q4'!$A:$A,0)),"") | O64: =IFERROR(INDEX('權數表原始_上櫃114Q4'!$CF:$CF,MATCH(VALUE($B64),'權數表原始_上櫃114Q4'!$A:$A,0)),"") | P64: =N64+O64 | Q64: =P64-IFERROR(INDEX('權數表原始_上櫃114Q4'!$CG:$CG,MATCH(VALUE($B64),'權數表原始_上櫃114Q4'!$A:$A,0)),"") | R64: 資金貸於他人(25)；營業收入、營業利益或稅前純益變動較大(22)；財務比率不佳(20)；財務主管辭職(20)；會計主管辭職(20)；背書保證(15)
A65: 上櫃 | B65: 6465 | C65: 威潤 | D65: 申宛云 | E65: 吳佳蓉 | F65: 台北巿內湖區潭美街539號6樓 | G65: 資誠聯合會計師事務所 | H65: 于智帆 | I65: 葉翠苗 | J65: 0.86 | K65: 10.43 | L65: 無保留意見 | M65: 115/03/04 | N65: =IFERROR(INDEX('權數表原始_上櫃114Q4'!$BN:$BN,MATCH(VALUE($B65),'權數表原始_上櫃114Q4'!$A:$A,0)),"") | O65: =IFERROR(INDEX('權數表原始_上櫃114Q4'!$CF:$CF,MATCH(VALUE($B65),'權數表原始_上櫃114Q4'!$A:$A,0)),"") | P65: =N65+O65 | Q65: =P65-IFERROR(INDEX('權數表原始_上櫃114Q4'!$CG:$CG,MATCH(VALUE($B65),'權數表原始_上櫃114Q4'!$A:$A,0)),"") | R65: 關係企業之交易(33)；營業收入、營業利益或稅前純益變動較大(29)；會計主管辭職(20)；董監事持股異動(15)；財務比率不佳(10)；獨立董事辭職(10)；董事辭職(5)
A66: 上市 | B66: 1235 | C66: 興泰 | D66: 邱棕晉 | E66: 美安生化科技股份有限公司(代表人楊淑樺) | F66: 高雄市仁武區高楠公路10號 | G66: 群智聯合會計師事務所 | H66: 呂松裕 | I66: 張鈞富 | J66: -0.03 | K66: 63.69 | L66: 無保留意見(強調事項或其他事項)-其他 | M66: 115/03/13 | N66: =IFERROR(INDEX('權數表原始_上市114Q4'!$BN:$BN,MATCH(VALUE($B66),'權數表原始_上市114Q4'!$A:$A,0)),"") | O66: =IFERROR(INDEX('權數表原始_上市114Q4'!$CF:$CF,MATCH(VALUE($B66),'權數表原始_上市114Q4'!$A:$A,0)),"") | P66: =N66+O66 | Q66: =P66-IFERROR(INDEX('權數表原始_上市114Q4'!$CG:$CG,MATCH(VALUE($B66),'權數表原始_上市114Q4'!$A:$A,0)),"") | R66: 財務比率不佳(50)；非流動之股權投資占權益比重較高(30)；營業收入、營業利益或稅前純益變動較大(21)；最近一年內有訴訟事件對公司財務業務有(20)
A67: 上櫃 | B67: 2066 | C67: 世德 | D67: 林育安(嘉衛代) | E67: 陳光裕 | F67: 高雄市大寮區(831)大發工業區華西路20號 | G67: 安侯建業聯合會計師事務所 | H67: 陳永祥 | I67: 許振隆 | J67: 1.34 | K67: 47.89 | L67: 無保留意見 | M67: 115/03/30 | N67: =IFERROR(INDEX('權數表原始_上櫃114Q4'!$BN:$BN,MATCH(VALUE($B67),'權數表原始_上櫃114Q4'!$A:$A,0)),"") | O67: =IFERROR(INDEX('權數表原始_上櫃114Q4'!$CF:$CF,MATCH(VALUE($B67),'權數表原始_上櫃114Q4'!$A:$A,0)),"") | P67: =N67+O67 | Q67: =P67-IFERROR(INDEX('權數表原始_上櫃114Q4'!$CG:$CG,MATCH(VALUE($B67),'權數表原始_上櫃114Q4'!$A:$A,0)),"") | R67: 資金貸於他人(30)；財務比率不佳(25)；會計主管辭職(20)；財務主管或會計主管或內稽主管是否與董(20)；營業收入、營業利益或稅前純益變動較大(16)；總經理辭職(10)
A68: 上櫃 | B68: 3339 | C68: 泰谷 | D68: 林育安(孟真代) | E68: 蔡兆全 | F68: 南投縣南投市自強三路18號 | G68: 安侯建業聯合會計師事務所 | H68: 張淑瑩 | I68: 區耀軍 | J68: -2 | K68: 11.05 | L68: 無保留意見 | M68: 115/03/03 | N68: =IFERROR(INDEX('權數表原始_上櫃114Q4'!$BN:$BN,MATCH(VALUE($B68),'權數表原始_上櫃114Q4'!$A:$A,0)),"") | O68: =IFERROR(INDEX('權數表原始_上櫃114Q4'!$CF:$CF,MATCH(VALUE($B68),'權數表原始_上櫃114Q4'!$A:$A,0)),"") | P68: =N68+O68 | Q68: =P68-IFERROR(INDEX('權數表原始_上櫃114Q4'!$CG:$CG,MATCH(VALUE($B68),'權數表原始_上櫃114Q4'!$A:$A,0)),"") | R68: 財務比率不佳(50)；營業收入、營業利益或稅前純益變動較大(26)；董事長質權設定達其實際持有股數五O%(20)；董事、監察人質權設定達全體董監實際持(15)；獨立董事辭職(10)
A69: 上市 | B69: 6152 | C69: 百一 | D69: 彥銨代伯強 | E69: 許錦輝 | F69: 桃園市中壢區自強一路3號 | G69: 安永聯合會計師事務所 | H69: 羅筱靖 | I69: 陳國帥 | J69: -1.47 | K69: 7.46 | L69: 無保留意見 | M69: 115/03/12 | N69: =IFERROR(INDEX('權數表原始_上市114Q4'!$BN:$BN,MATCH(VALUE($B69),'權數表原始_上市114Q4'!$A:$A,0)),"") | O69: =IFERROR(INDEX('權數表原始_上市114Q4'!$CF:$CF,MATCH(VALUE($B69),'權數表原始_上市114Q4'!$A:$A,0)),"") | P69: =N69+O69 | Q69: =P69-IFERROR(INDEX('權數表原始_上市114Q4'!$CG:$CG,MATCH(VALUE($B69),'權數表原始_上市114Q4'!$A:$A,0)),"") | R69: 財務比率不佳(65)；營業收入、營業利益或稅前純益變動較大(26)；資金貸於他人(20)；每股淨值偏低(10)
A70: 上市 | B70: 2514 | C70: 龍邦 | D70: 郭秀春 | E70: 劉偉龍 | F70: 台北市中正區忠孝西路一段50號9樓 | G70: 安永聯合會計師事務所 | H70: 黃子評 | I70: 林素雯 | J70: 1.85 | K70: 35.43 | L70: 無保留意見(強調事項或其他事項)-採用其他會計師查核(核閱)報告且欲區分責任 | M70: 115/03/11 | N70: =IFERROR(INDEX('權數表原始_上市114Q4'!$BN:$BN,MATCH(VALUE($B70),'權數表原始_上市114Q4'!$A:$A,0)),"") | O70: =IFERROR(INDEX('權數表原始_上市114Q4'!$CF:$CF,MATCH(VALUE($B70),'權數表原始_上市114Q4'!$A:$A,0)),"") | P70: =N70+O70 | Q70: =P70-IFERROR(INDEX('權數表原始_上市114Q4'!$CG:$CG,MATCH(VALUE($B70),'權數表原始_上市114Q4'!$A:$A,0)),"") | R70: 財務比率不佳(35)；董事、監察人質權設定達全體董監實際持(20)；董事長質權設定達其實際持有股數五O%(20)；最近一年內有訴訟事件對公司財務業務有(20)；營業收入、營業利益或稅前純益變動較大(10)；非流動之股權投資占權益比重較高(10)；背書保證(5)
A71: 上市 | B71: 6869 | C71: 雲豹能源 | D71: 李佩琳 | E71: 廖福生 | F71: 台北市內湖區基湖路1號4樓之1 | G71: 安侯建業聯合會計師事務所 | H71: 洪士剛 | I71: 傅泓文 | J71: -4.2 | K71: 36.31 | L71: 無保留意見(強調事項或其他事項)-採用其他會計師查核(核閱)報告且欲區分責任 | M71: 115/03/12 | N71: =IFERROR(INDEX('權數表原始_上市114Q4'!$BN:$BN,MATCH(VALUE($B71),'權數表原始_上市114Q4'!$A:$A,0)),"") | O71: =IFERROR(INDEX('權數表原始_上市114Q4'!$CF:$CF,MATCH(VALUE($B71),'權數表原始_上市114Q4'!$A:$A,0)),"") | P71: =N71+O71 | Q71: =P71-IFERROR(INDEX('權數表原始_上市114Q4'!$CG:$CG,MATCH(VALUE($B71),'權數表原始_上市114Q4'!$A:$A,0)),"") | R71: 財務比率不佳(35)；營業收入、營業利益或稅前純益變動較大(30)；資金貸於他人(20)；非流動之股權投資占權益比重較高(20)；背書保證(15)
A72: 上櫃 | B72: 3360 | C72: 尚立 | D72: 彥銨代伯強 | E72: 簡剛民 | F72: 台北市內湖區洲子街76號6樓 | G72: 勤業眾信聯合會計師事務所 | H72: 張至誼 | I72: 施錦川 | J72: -0.48 | K72: 10.79 | L72: 無保留意見 | M72: 115/03/13 | N72: =IFERROR(INDEX('權數表原始_上櫃114Q4'!$BN:$BN,MATCH(VALUE($B72),'權數表原始_上櫃114Q4'!$A:$A,0)),"") | O72: =IFERROR(INDEX('權數表原始_上櫃114Q4'!$CF:$CF,MATCH(VALUE($B72),'權數表原始_上櫃114Q4'!$A:$A,0)),"") | P72: =N72+O72 | Q72: =P72-IFERROR(INDEX('權數表原始_上櫃114Q4'!$CG:$CG,MATCH(VALUE($B72),'權數表原始_上櫃114Q4'!$A:$A,0)),"") | R72: 財務比率不佳(45)；背書保證(25)；資金貸於他人(20)；財務主管辭職(20)；營業收入、營業利益或稅前純益變動較大(9)
A73: 上櫃 | B73: 5324 | C73: 士開 | D73: 李靜平 | E73: 許玉山 | F73: 台北市中山北路六段九十號八樓 | G73: 安侯建業聯合會計師事務所 | H73: 潘俊名 | I73: 陳宗哲 | J73: -0.05 | K73: 6.6 | L73: 無保留意見(強調事項或其他事項)-採用其他會計師查核(核閱)報告且欲區分責任 | M73: 115/03/05 | N73: =IFERROR(INDEX('權數表原始_上櫃114Q4'!$BN:$BN,MATCH(VALUE($B73),'權數表原始_上櫃114Q4'!$A:$A,0)),"") | O73: =IFERROR(INDEX('權數表原始_上櫃114Q4'!$CF:$CF,MATCH(VALUE($B73),'權數表原始_上櫃114Q4'!$A:$A,0)),"") | P73: =N73+O73 | Q73: =P73-IFERROR(INDEX('權數表原始_上櫃114Q4'!$CG:$CG,MATCH(VALUE($B73),'權數表原始_上櫃114Q4'!$A:$A,0)),"") | R73: 財務比率不佳(85)；營業收入、營業利益或稅前純益變動較大(24)；每股淨值偏低(10)
A74: 上櫃 | B74: 8087 | C74: 麗升能源 | D74: 郭秀春 | E74: 林麗珍 | F74: 110404台北市信義區松高路1號10樓之1 | G74: 安侯建業聯合會計師事務所 | H74: 張淑瑩 | I74: 黃欣婷 | J74: -1.32 | K74: 20 | L74: 無保留意見 | M74: 115/03/11 | N74: =IFERROR(INDEX('權數表原始_上櫃114Q4'!$BN:$BN,MATCH(VALUE($B74),'權數表原始_上櫃114Q4'!$A:$A,0)),"") | O74: =IFERROR(INDEX('權數表原始_上櫃114Q4'!$CF:$CF,MATCH(VALUE($B74),'權數表原始_上櫃114Q4'!$A:$A,0)),"") | P74: =N74+O74 | Q74: =P74-IFERROR(INDEX('權數表原始_上櫃114Q4'!$CG:$CG,MATCH(VALUE($B74),'權數表原始_上櫃114Q4'!$A:$A,0)),"") | R74: 財務比率不佳(55)；營業收入、營業利益或稅前純益變動較大(29)；背書保證(15)；非流動之股權投資占權益比重較高(10)；當期非流動之股權投資增減金額占權益比(10)
A75: 上櫃 | B75: 8906 | C75: 花王 | D75: 怡秀代若瑛 | E75: 謝宗翰 | F75: 新北市土城區中山路六十五號 | G75: 資誠聯合會計師事務所 | H75: 林佳鴻 | I75: 文雅芳 | J75: -0.78 | K75: 11.18 | L75: 無保留意見 | M75: 115/03/04 | N75: =IFERROR(INDEX('權數表原始_上櫃114Q4'!$BN:$BN,MATCH(VALUE($B75),'權數表原始_上櫃114Q4'!$A:$A,0)),"") | O75: =IFERROR(INDEX('權數表原始_上櫃114Q4'!$CF:$CF,MATCH(VALUE($B75),'權數表原始_上櫃114Q4'!$A:$A,0)),"") | P75: =N75+O75 | Q75: =P75-IFERROR(INDEX('權數表原始_上櫃114Q4'!$CG:$CG,MATCH(VALUE($B75),'權數表原始_上櫃114Q4'!$A:$A,0)),"") | R75: 財務比率不佳(75)；營業收入、營業利益或稅前純益變動較大(24)；非流動之股權投資占權益比重較高(20)
A76: 上櫃 | B76: 8291 | C76: 尚茂 | D76: 李靜平 | E76: 佐佐木Beji | F76: 桃園市大園區濱海路二段208號 | G76: 勤業眾信聯合會計師事務所 | H76: 林淑如 | I76: 陳昭伶 | J76: -1.95 | K76: 4.23 | L76: 無保留意見(強調事項或其他事項)-其他 | M76: 115/02/13 | N76: =IFERROR(INDEX('權數表原始_上櫃114Q4'!$BN:$BN,MATCH(VALUE($B76),'權數表原始_上櫃114Q4'!$A:$A,0)),"") | O76: =IFERROR(INDEX('權數表原始_上櫃114Q4'!$CF:$CF,MATCH(VALUE($B76),'權數表原始_上櫃114Q4'!$A:$A,0)),"") | P76: =N76+O76 | Q76: =P76-IFERROR(INDEX('權數表原始_上櫃114Q4'!$CG:$CG,MATCH(VALUE($B76),'權數表原始_上櫃114Q4'!$A:$A,0)),"") | R76: 財務比率不佳(70)；營業收入、營業利益或稅前純益變動較大(20)；每股淨值偏低(15)；獨立董事辭職(10)；關係企業之交易(3)
A77: 上市 | B77: 1795 | C77: 美時 | D77: 黃冠達 | E77: Vilhelm Robert Wessman | F77: 臺北市信義區松仁路277號17樓 | G77: 安侯建業聯合會計師事務所 | H77: 鄭安志 | I77: 周寶蓮 | J77: 18.14 | K77: 90.48 | L77: 無保留意見 | M77: 115/03/12 | N77: =IFERROR(INDEX('權數表原始_上市114Q4'!$BN:$BN,MATCH(VALUE($B77),'權數表原始_上市114Q4'!$A:$A,0)),"") | O77: =IFERROR(INDEX('權數表原始_上市114Q4'!$CF:$CF,MATCH(VALUE($B77),'權數表原始_上市114Q4'!$A:$A,0)),"") | P77: =N77+O77 | Q77: =P77-IFERROR(INDEX('權數表原始_上市114Q4'!$CG:$CG,MATCH(VALUE($B77),'權數表原始_上市114Q4'!$A:$A,0)),"") | R77: 財務比率不佳(60)；資金貸於他人(40)；研發主管辭職(10)；營業收入、營業利益或稅前純益變動較大(4)；關係企業之交易(3)
A78: 上櫃 | B78: 4513 | C78: 福裕 | D78: 趙彥銨 | E78: 林聰麟 | F78: 彰化縣伸港鄉興工路34號 | G78: 安永聯合會計師事務所 | H78: 陳政初 | I78: 洪國森 | J78: -1.79 | K78: 10.06 | L78: 無保留意見(強調事項或其他事項)-採用其他會計師查核(核閱)報告且欲區分責任 | M78: 115/03/09 | N78: =IFERROR(INDEX('權數表原始_上櫃114Q4'!$BN:$BN,MATCH(VALUE($B78),'權數表原始_上櫃114Q4'!$A:$A,0)),"") | O78: =IFERROR(INDEX('權數表原始_上櫃114Q4'!$CF:$CF,MATCH(VALUE($B78),'權數表原始_上櫃114Q4'!$A:$A,0)),"") | P78: =N78+O78 | Q78: =P78-IFERROR(INDEX('權數表原始_上櫃114Q4'!$CG:$CG,MATCH(VALUE($B78),'權數表原始_上櫃114Q4'!$A:$A,0)),"") | R78: 財務比率不佳(60)；營業收入、營業利益或稅前純益變動較大(24)；非流動之股權投資占權益比重較高(20)；採用權益法之關聯企業及合資損益份額((10)；關係企業之交易(3)
A79: 上櫃 | B79: 5263 | C79: 智崴 | D79: 宛云代伯強 | E79: 歐陽志宏 | F79: 高雄市前鎮區復興四路9號 | G79: 勤業眾信聯合會計師事務所 | H79: 吳秋燕 | I79: 郭麗園 | J79: -2.87 | K79: 52.29 | L79: 無保留意見 | M79: 115/03/12 | N79: =IFERROR(INDEX('權數表原始_上櫃114Q4'!$BN:$BN,MATCH(VALUE($B79),'權數表原始_上櫃114Q4'!$A:$A,0)),"") | O79: =IFERROR(INDEX('權數表原始_上櫃114Q4'!$CF:$CF,MATCH(VALUE($B79),'權數表原始_上櫃114Q4'!$A:$A,0)),"") | P79: =N79+O79 | Q79: =P79-IFERROR(INDEX('權數表原始_上櫃114Q4'!$CG:$CG,MATCH(VALUE($B79),'權數表原始_上櫃114Q4'!$A:$A,0)),"") | R79: 財務比率不佳(35)；董事長質權設定達其實際持有股數五O%(25)；總經理質權設定達其實際持有股數五O%(25)；營業收入、營業利益或稅前純益變動較大(22)；採用權益法之關聯企業及合資損益份額((10)
A80: 上櫃 | B80: 8059 | C80: 凱碩 | D80: 李佩琳 | E80: 章瑛 | F80: 新北市深坑區北深路三段141巷14號 | G80: 安永聯合會計師事務所 | H80: 陳智忠 | I80: 余倩如 | J80: -2.39 | K80: 5.75 | L80: 無保留意見(強調事項或其他事項)-前期由其他會計師查核 | M80: 115/03/11 | N80: =IFERROR(INDEX('權數表原始_上櫃114Q4'!$BN:$BN,MATCH(VALUE($B80),'權數表原始_上櫃114Q4'!$A:$A,0)),"") | O80: =IFERROR(INDEX('權數表原始_上櫃114Q4'!$CF:$CF,MATCH(VALUE($B80),'權數表原始_上櫃114Q4'!$A:$A,0)),"") | P80: =N80+O80 | Q80: =P80-IFERROR(INDEX('權數表原始_上櫃114Q4'!$CG:$CG,MATCH(VALUE($B80),'權數表原始_上櫃114Q4'!$A:$A,0)),"") | R80: 財務比率不佳(50)；關係企業之交易(19)；資金貸於他人(15)；營業收入、營業利益或稅前純益變動較大(13)；背書保證(10)；每股淨值偏低(10) | S80: 新承接（審計510 期初餘額）
A81: 上櫃 | B81: 2734 | C81: 易飛網 | D81: 趙彥銨 | E81: 周昀生 | F81: 台北市中正區衡陽路51號2樓之1 | G81: 勤業眾信聯合會計師事務所 | H81: 蘇郁琇 | I81: 彭詩玄 | J81: -1.42 | K81: 11.4 | L81: 無保留意見(強調事項或其他事項)-採用其他會計師查核(核閱)報告且欲區分責任、前期由其他會計師查核 | M81: 115/03/25 | N81: =IFERROR(INDEX('權數表原始_上櫃114Q4'!$BN:$BN,MATCH(VALUE($B81),'權數表原始_上櫃114Q4'!$A:$A,0)),"") | O81: =IFERROR(INDEX('權數表原始_上櫃114Q4'!$CF:$CF,MATCH(VALUE($B81),'權數表原始_上櫃114Q4'!$A:$A,0)),"") | P81: =N81+O81 | Q81: =P81-IFERROR(INDEX('權數表原始_上櫃114Q4'!$CG:$CG,MATCH(VALUE($B81),'權數表原始_上櫃114Q4'!$A:$A,0)),"") | R81: 採用權益法之關聯企業及合資損益份額((40)；營業收入、營業利益或稅前純益變動較大(21)；更換會計師（非屬會計師事務所內部調整(20)；財務比率不佳(10)；非流動之股權投資占權益比重較高(10)；關係企業之交易(5)；董事長質權設定達其實際持有股數五O%(5)；總經理質權設定達其實際持有股數五O%(5) | S81: 新承接（審計510 期初餘額）
A82: 上櫃 | B82: 3709 | C82: 鑫聯大投控 | D82: 黃靖雅 | E82: 黃偉祥 | F82: 台北市南港區經貿二路189號22樓 | G82: 資誠聯合會計師事務所 | H82: 王銘義 | I82: 林一帆 | J82: 7.11 | K82: 29.14 | L82: 無保留意見 | M82: 115/03/09 | N82: =IFERROR(INDEX('權數表原始_上櫃114Q4'!$BN:$BN,MATCH(VALUE($B82),'權數表原始_上櫃114Q4'!$A:$A,0)),"") | O82: =IFERROR(INDEX('權數表原始_上櫃114Q4'!$CF:$CF,MATCH(VALUE($B82),'權數表原始_上櫃114Q4'!$A:$A,0)),"") | P82: =N82+O82 | Q82: =P82-IFERROR(INDEX('權數表原始_上櫃114Q4'!$CG:$CG,MATCH(VALUE($B82),'權數表原始_上櫃114Q4'!$A:$A,0)),"") | R82: 財務比率不佳(40)；營業收入、營業利益或稅前純益變動較大(27)；背書保證(25)；資金貸於他人(20)；關係企業之交易(4)
A83: 上櫃 | B83: 5464 | C83: 霖宏 | D83: 廖昭慈 | E83: 張枋霖 | F83: 嘉義縣民雄鄉福樂村中山路6號 | G83: 安 永 聯 合 會 計 師 事 務 所 | H83: 涂清淵 | I83: 羅文振 | J83: -2.59 | K83: 16.27 | L83: 無保留意見 | M83: 115/03/11 | N83: =IFERROR(INDEX('權數表原始_上櫃114Q4'!$BN:$BN,MATCH(VALUE($B83),'權數表原始_上櫃114Q4'!$A:$A,0)),"") | O83: =IFERROR(INDEX('權數表原始_上櫃114Q4'!$CF:$CF,MATCH(VALUE($B83),'權數表原始_上櫃114Q4'!$A:$A,0)),"") | P83: =N83+O83 | Q83: =P83-IFERROR(INDEX('權數表原始_上櫃114Q4'!$CG:$CG,MATCH(VALUE($B83),'權數表原始_上櫃114Q4'!$A:$A,0)),"") | R83: 財務比率不佳(55)；資金貸於他人(20)；財務主管或會計主管或內稽主管是否與董(20)；營業收入、營業利益或稅前純益變動較大(16)；背書保證(5)
A84: 上市 | B84: 9946 | C84: 三發地產 | D84: 曾冠程 | E84: 鍾鼎晟 | F84: 台北市松山區八德路3段30號12樓 | G84: 安侯建業聯合會計師事務所 | H84: 韓沂璉 | I84: 黃欣婷 | J84: 1.52 | K84: 20.75 | L84: 無保留意見(強調事項或其他事項) | M84: 115/03/03 | N84: =IFERROR(INDEX('權數表原始_上市114Q4'!$BN:$BN,MATCH(VALUE($B84),'權數表原始_上市114Q4'!$A:$A,0)),"") | O84: =IFERROR(INDEX('權數表原始_上市114Q4'!$CF:$CF,MATCH(VALUE($B84),'權數表原始_上市114Q4'!$A:$A,0)),"") | P84: =N84+O84 | Q84: =P84-IFERROR(INDEX('權數表原始_上市114Q4'!$CG:$CG,MATCH(VALUE($B84),'權數表原始_上市114Q4'!$A:$A,0)),"") | R84: 財務比率不佳(60)；關係企業之交易(33)；營業收入、營業利益或稅前純益變動較大(13)；背書保證(5)；董事辭職(5)
A85: 上市 | B85: 2007 | C85: 燁興 | D85: 黃姵蓉 | E85: 吳林茂 | F85: 高雄市岡山區白米里寶米路369號 | G85: 國富浩華聯合會計師事務所 | H85: 黃致富 | I85: 黃鈴雯 | J85: -2.24 | K85: 7.96 | L85: 無保留意見 | M85: 115/03/06 | N85: =IFERROR(INDEX('權數表原始_上市114Q4'!$BN:$BN,MATCH(VALUE($B85),'權數表原始_上市114Q4'!$A:$A,0)),"") | O85: =IFERROR(INDEX('權數表原始_上市114Q4'!$CF:$CF,MATCH(VALUE($B85),'權數表原始_上市114Q4'!$A:$A,0)),"") | P85: =N85+O85 | Q85: =P85-IFERROR(INDEX('權數表原始_上市114Q4'!$CG:$CG,MATCH(VALUE($B85),'權數表原始_上市114Q4'!$A:$A,0)),"") | R85: 財務比率不佳(55)；非流動之股權投資占權益比重較高(30)；採用權益法之關聯企業及合資損益份額((10)；每股淨值偏低(10)；營業收入、營業利益或稅前純益變動較大(7)；關係企業之交易(3)
A86: 上市 | B86: 2509 | C86: 全坤建 | D86: 陳怡秀 | E86: 李勇毅 | F86: 台北市內湖區新湖二路329號6樓 | G86: 安侯建業聯合會計師事務所 | H86: 黃欣婷 | I86: 曾國禓 | J86: -0.8 | K86: 17.42 | L86: 無保留意見 | M86: 115/03/11 | N86: =IFERROR(INDEX('權數表原始_上市114Q4'!$BN:$BN,MATCH(VALUE($B86),'權數表原始_上市114Q4'!$A:$A,0)),"") | O86: =IFERROR(INDEX('權數表原始_上市114Q4'!$CF:$CF,MATCH(VALUE($B86),'權數表原始_上市114Q4'!$A:$A,0)),"") | P86: =N86+O86 | Q86: =P86-IFERROR(INDEX('權數表原始_上市114Q4'!$CG:$CG,MATCH(VALUE($B86),'權數表原始_上市114Q4'!$A:$A,0)),"") | R86: 財務比率不佳(80)；營業收入、營業利益或稅前純益變動較大(30)；董事長質權設定達其實際持有股數五O%(5)
A87: 上櫃 | B87: 4745 | C87: 合富-KY | D87: 申宛云 | E87: 王瓊芝 | F87: Suite 102, Cannon Place, North Sound Rd., George Town | G87: 安侯建業聯合會計師事務所 | H87: 謝秋華 | I87: 周寶蓮 | J87: -3.18 | K87: 37.06 | L87: 無保留意見 | M87: 115/03/13 | N87: =IFERROR(INDEX('權數表原始_上櫃114Q4'!$BN:$BN,MATCH(VALUE($B87),'權數表原始_上櫃114Q4'!$A:$A,0)),"") | O87: =IFERROR(INDEX('權數表原始_上櫃114Q4'!$CF:$CF,MATCH(VALUE($B87),'權數表原始_上櫃114Q4'!$A:$A,0)),"") | P87: =N87+O87 | Q87: =P87-IFERROR(INDEX('權數表原始_上櫃114Q4'!$CG:$CG,MATCH(VALUE($B87),'權數表原始_上櫃114Q4'!$A:$A,0)),"") | R87: 財務比率不佳(30)；營業收入、營業利益或稅前純益變動較大(25)；資金貸於他人(25)；會計主管辭職(20)；背書保證(5)；董監事持股異動(5)；董事辭職(5) | S87: KY
A88: 上櫃 | B88: 4903 | C88: 聯光通 | D88: 郭秀春 | E88: 林郁昌 | F88: 新竹市科學園區研新四路12號 | G88: 安侯建業聯合會計師事務所 | H88: 謝秋華 | I88: 周寶蓮 | J88: 1.02 | K88: 11.02 | L88: 無保留意見 | M88: 115/01/28 | N88: =IFERROR(INDEX('權數表原始_上櫃114Q4'!$BN:$BN,MATCH(VALUE($B88),'權數表原始_上櫃114Q4'!$A:$A,0)),"") | O88: =IFERROR(INDEX('權數表原始_上櫃114Q4'!$CF:$CF,MATCH(VALUE($B88),'權數表原始_上櫃114Q4'!$A:$A,0)),"") | P88: =N88+O88 | Q88: =P88-IFERROR(INDEX('權數表原始_上櫃114Q4'!$CG:$CG,MATCH(VALUE($B88),'權數表原始_上櫃114Q4'!$A:$A,0)),"") | R88: 非流動之股權投資占權益比重較高(30)；營業收入、營業利益或稅前純益變動較大(29)；財務比率不佳(20)；當期非流動之股權投資增減金額占權益比(20)；關係企業之交易(16)
A89: 上櫃 | B89: 6130 | C89: 上亞科技 | D89: 徐雅琳 | E89: 蔡文杰 | F89: 臺北市內湖區行愛路77巷63號6樓 | G89: 國富浩華聯合會計師事務所 | H89: 王戊昌 | I89: 陳桂美 | J89: -1.72 | K89: 12.31 | L89: 無保留意見 | M89: 115/03/13 | N89: =IFERROR(INDEX('權數表原始_上櫃114Q4'!$BN:$BN,MATCH(VALUE($B89),'權數表原始_上櫃114Q4'!$A:$A,0)),"") | O89: =IFERROR(INDEX('權數表原始_上櫃114Q4'!$CF:$CF,MATCH(VALUE($B89),'權數表原始_上櫃114Q4'!$A:$A,0)),"") | P89: =N89+O89 | Q89: =P89-IFERROR(INDEX('權數表原始_上櫃114Q4'!$CG:$CG,MATCH(VALUE($B89),'權數表原始_上櫃114Q4'!$A:$A,0)),"") | R89: 財務比率不佳(40)；營業收入、營業利益或稅前純益變動較大(25)；會計主管辭職(20)；董事長辭職(10)；總經理辭職(10)；獨立董事辭職(10)
A90: 上市 | B90: 2905 | C90: 三商 | D90: 詹孟真 | E90: 陳翔立 | F90: 台北市建國北路二段145號地下1樓及1~18樓 | G90: 立本台灣聯合會計師事務所 | H90: 許坤錫 | I90: 張書成 | J90: 0.71 | K90: 14.97 | L90: 無保留意見(強調事項或其他事項)-採用其他會計師查核(核閱)報告且欲區分責任 | M90: 115/03/13 | N90: =IFERROR(INDEX('權數表原始_上市114Q4'!$BN:$BN,MATCH(VALUE($B90),'權數表原始_上市114Q4'!$A:$A,0)),"") | O90: =IFERROR(INDEX('權數表原始_上市114Q4'!$CF:$CF,MATCH(VALUE($B90),'權數表原始_上市114Q4'!$A:$A,0)),"") | P90: =N90+O90 | Q90: =P90-IFERROR(INDEX('權數表原始_上市114Q4'!$CG:$CG,MATCH(VALUE($B90),'權數表原始_上市114Q4'!$A:$A,0)),"") | R90: 財務比率不佳(30)；非流動之股權投資占權益比重較高(30)；董事長質權設定達其實際持有股數五O%(20)；總經理質權設定達其實際持有股數五O%(20)；董事、監察人質權設定達全體董監實際持(10)；營業收入、營業利益或稅前純益變動較大(4)
A91: 上櫃 | B91: 3162 | C91: 精確 | D91: 邱棕晉 | E91: 胡白莎 | F91: 桃園市新屋區社子里二鄰中興路938號 | G91: 資誠聯合會計師事務所 | H91: 支秉鈞 | I91: 徐明釧 | J91: 1.7 | K91: 23.42 | L91: 無保留意見 | M91: 115/03/13 | N91: =IFERROR(INDEX('權數表原始_上櫃114Q4'!$BN:$BN,MATCH(VALUE($B91),'權數表原始_上櫃114Q4'!$A:$A,0)),"") | O91: =IFERROR(INDEX('權數表原始_上櫃114Q4'!$CF:$CF,MATCH(VALUE($B91),'權數表原始_上櫃114Q4'!$A:$A,0)),"") | P91: =N91+O91 | Q91: =P91-IFERROR(INDEX('權數表原始_上櫃114Q4'!$CG:$CG,MATCH(VALUE($B91),'權數表原始_上櫃114Q4'!$A:$A,0)),"") | R91: 財務比率不佳(30)；營業收入、營業利益或稅前純益變動較大(29)；資金貸於他人(20)；背書保證(15)；關係企業之交易(10)；董事辭職(5)；董監事報酬不合理(5)
A92: 上市 | B92: 5608 | C92: 四維航 | D92: 張怡真 | E92: 藍心琪 | F92: 台北市105松山區復興北路167號16樓 | G92: 安侯建業聯合會計師事務所 | H92: 池世欽 | I92: 曾國禓 | J92: -0.13 | K92: 24.34 | L92: 無保留意見 | M92: 115/03/10 | N92: =IFERROR(INDEX('權數表原始_上市114Q4'!$BN:$BN,MATCH(VALUE($B92),'權數表原始_上市114Q4'!$A:$A,0)),"") | O92: =IFERROR(INDEX('權數表原始_上市114Q4'!$CF:$CF,MATCH(VALUE($B92),'權數表原始_上市114Q4'!$A:$A,0)),"") | P92: =N92+O92 | Q92: =P92-IFERROR(INDEX('權數表原始_上市114Q4'!$CG:$CG,MATCH(VALUE($B92),'權數表原始_上市114Q4'!$A:$A,0)),"") | R92: 財務比率不佳(45)；資金貸於他人(27)；背書保證(25)；營業收入、營業利益或稅前純益變動較大(16)
A93: 上市 | B93: 1436 | C93: 華友聯 | D93: 郭秀春 | E93: 陸炤廷 | F93: 高雄市鳳山區文龍路85號11樓 | G93: 勤業眾信聯合會計師事務所 | H93: 陳秀雯 | I93: 王兆群 | J93: 5.39 | K93: 33.48 | L93: 無保留意見 | M93: 115/02/26 | N93: =IFERROR(INDEX('權數表原始_上市114Q4'!$BN:$BN,MATCH(VALUE($B93),'權數表原始_上市114Q4'!$A:$A,0)),"") | O93: =IFERROR(INDEX('權數表原始_上市114Q4'!$CF:$CF,MATCH(VALUE($B93),'權數表原始_上市114Q4'!$A:$A,0)),"") | P93: =N93+O93 | Q93: =P93-IFERROR(INDEX('權數表原始_上市114Q4'!$CG:$CG,MATCH(VALUE($B93),'權數表原始_上市114Q4'!$A:$A,0)),"") | R93: 財務比率不佳(55)；背書保證(35)；營業收入、營業利益或稅前純益變動較大(17)；董監事持股異動(5)
A94: 上市 | B94: 2348 | C94: 海悅 | D94: 申宛云 | E94: 黃希文 | F94: 台北市松山區敦化北路260號7樓 | G94: 勤業眾信聯合會計師事務所 | H94: 劉紋伶 | I94: 陳培德 | J94: 6.85 | K94: 45.9 | L94: 無保留意見 | M94: 115/03/31 | N94: =IFERROR(INDEX('權數表原始_上市114Q4'!$BN:$BN,MATCH(VALUE($B94),'權數表原始_上市114Q4'!$A:$A,0)),"") | O94: =IFERROR(INDEX('權數表原始_上市114Q4'!$CF:$CF,MATCH(VALUE($B94),'權數表原始_上市114Q4'!$A:$A,0)),"") | P94: =N94+O94 | Q94: =P94-IFERROR(INDEX('權數表原始_上市114Q4'!$CG:$CG,MATCH(VALUE($B94),'權數表原始_上市114Q4'!$A:$A,0)),"") | R94: 財務比率不佳(65)；非流動之股權投資占權益比重較高(20)；背書保證(15)；營業收入、營業利益或稅前純益變動較大(12)
A95: 上櫃 | B95: 2726 | C95: 雅茗-KY | D95: 申宛云 | E95: 吳伯超 | F95: 臺北市內湖區新湖一路77號6樓 | G95: 勤業眾信聯合會計師事務所 | H95: 張至誼 | I95: 洪國田 | J95: -3.55 | K95: 10.03 | L95: 無保留意見 | M95: 115/03/31 | N95: =IFERROR(INDEX('權數表原始_上櫃114Q4'!$BN:$BN,MATCH(VALUE($B95),'權數表原始_上櫃114Q4'!$A:$A,0)),"") | O95: =IFERROR(INDEX('權數表原始_上櫃114Q4'!$CF:$CF,MATCH(VALUE($B95),'權數表原始_上櫃114Q4'!$A:$A,0)),"") | P95: =N95+O95 | Q95: =P95-IFERROR(INDEX('權數表原始_上櫃114Q4'!$CG:$CG,MATCH(VALUE($B95),'權數表原始_上櫃114Q4'!$A:$A,0)),"") | R95: 資金貸於他人(30)；財務比率不佳(30)；營業收入、營業利益或稅前純益變動較大(22)；背書保證(15)；董監事持股異動(15) | S95: KY
A96: 上市 | B96: 3043 | C96: 科風 | D96: 黃靖雅 | E96: 科飛投資股份有限公司 | F96: 新北市中和區連城路246號9樓 | G96: 德昌聯合會計師事務所 | H96: 林兆民 | I96: 史岱平 | J96: -2.67 | K96: 20.88 | L96: 無保留意見(強調事項或其他事項)-採用其他會計師查核(核閱)報告且欲區分責任 | M96: 115/03/12 | N96: =IFERROR(INDEX('權數表原始_上市114Q4'!$BN:$BN,MATCH(VALUE($B96),'權數表原始_上市114Q4'!$A:$A,0)),"") | O96: =IFERROR(INDEX('權數表原始_上市114Q4'!$CF:$CF,MATCH(VALUE($B96),'權數表原始_上市114Q4'!$A:$A,0)),"") | P96: =N96+O96 | Q96: =P96-IFERROR(INDEX('權數表原始_上市114Q4'!$CG:$CG,MATCH(VALUE($B96),'權數表原始_上市114Q4'!$A:$A,0)),"") | R96: 財務比率不佳(40)；非流動之股權投資占權益比重較高(30)；營業收入、營業利益或稅前純益變動較大(22)；資金貸於他人(20)
A97: 上市 | B97: 3576 | C97: 聯合再生 | D97: 黃冠達 | E97: 洪傳獻 | F97: 新竹科學工業園區新竹市力行三路7號 | G97: 勤業眾信聯合會計師事務所 | H97: 廖婉怡 | I97: 梁盛泰 | J97: -0.77 | K97: 6.38 | L97: 無保留意見(強調事項或其他事項)-採用其他會計師查核(核閱)報告且欲區分責任、前期由其他會計師查核 | M97: 115/03/13 | N97: =IFERROR(INDEX('權數表原始_上市114Q4'!$BN:$BN,MATCH(VALUE($B97),'權數表原始_上市114Q4'!$A:$A,0)),"") | O97: =IFERROR(INDEX('權數表原始_上市114Q4'!$CF:$CF,MATCH(VALUE($B97),'權數表原始_上市114Q4'!$A:$A,0)),"") | P97: =N97+O97 | Q97: =P97-IFERROR(INDEX('權數表原始_上市114Q4'!$CG:$CG,MATCH(VALUE($B97),'權數表原始_上市114Q4'!$A:$A,0)),"") | R97: 財務比率不佳(45)；最近一年內有訴訟事件對公司財務業務有(20)；營業收入、營業利益或稅前純益變動較大(17)；每股淨值偏低(10)；內稽主管辭職(10)；研發主管辭職(10) | S97: 新承接（審計510 期初餘額）
A98: 上市 | B98: 1444 | C98: 力麗 | D98: 曾冠程 | E98: 郭紹儀 | F98: 104台北市松江路162號11樓 | G98: 勤業眾信聯合會計師事務所 | H98: 黃毅民 | I98: 洪國田 | J98: -0.78 | K98: 9.74 | L98: 無保留意見(強調事項或其他事項)-採用其他會計師查核(核閱)報告且欲區分責任 | M98: 115/03/16 | N98: =IFERROR(INDEX('權數表原始_上市114Q4'!$BN:$BN,MATCH(VALUE($B98),'權數表原始_上市114Q4'!$A:$A,0)),"") | O98: =IFERROR(INDEX('權數表原始_上市114Q4'!$CF:$CF,MATCH(VALUE($B98),'權數表原始_上市114Q4'!$A:$A,0)),"") | P98: =N98+O98 | Q98: =P98-IFERROR(INDEX('權數表原始_上市114Q4'!$CG:$CG,MATCH(VALUE($B98),'權數表原始_上市114Q4'!$A:$A,0)),"") | R98: 財務比率不佳(35)；採用權益法之關聯企業及合資損益份額((20)；非流動之股權投資占權益比重較高(20)；營業收入、營業利益或稅前純益變動較大(16)；資金貸於他人(15)；每股淨值偏低(5)
A99: 上櫃 | B99: 4304 | C99: 勝昱 | D99: 姵蓉代伯強 | E99: 侯信立 | F99: 台北市松山區健康路152號3樓 | G99: 正風聯合會計師事務所 | H99: 賴家裕 | I99: 曾國富 | J99: -1.16 | K99: 5.15 | L99: 無保留意見(強調事項或其他事項)-前期由其他會計師查核 | M99: 115/03/31 | N99: =IFERROR(INDEX('權數表原始_上櫃114Q4'!$BN:$BN,MATCH(VALUE($B99),'權數表原始_上櫃114Q4'!$A:$A,0)),"") | O99: =IFERROR(INDEX('權數表原始_上櫃114Q4'!$CF:$CF,MATCH(VALUE($B99),'權數表原始_上櫃114Q4'!$A:$A,0)),"") | P99: =N99+O99 | Q99: =P99-IFERROR(INDEX('權數表原始_上櫃114Q4'!$CG:$CG,MATCH(VALUE($B99),'權數表原始_上櫃114Q4'!$A:$A,0)),"") | R99: 財務主管辭職(20)；會計主管辭職(20)；更換會計師（非屬會計師事務所內部調整(20)；財務比率不佳(10)；每股淨值偏低(10)；董監事持股異動(10)；獨立董事辭職(10)；營業收入、營業利益或稅前純益變動較大(6)；董事辭職(5) | S99: 新承接（審計510 期初餘額）
A100: 上櫃 | B100: 5386 | C100: 青雲 | D100: 劉瓊遙 | E100: 柯聰源 | F100: 新北市中和區中正路716號6樓 | G100: 眾智聯合會計師事務所 | H100: 楊永成 | I100: 游佩靜 | J100: 8.61 | K100: 25.71 | L100: 無保留意見 | M100: 115/03/03 | N100: =IFERROR(INDEX('權數表原始_上櫃114Q4'!$BN:$BN,MATCH(VALUE($B100),'權數表原始_上櫃114Q4'!$A:$A,0)),"") | O100: =IFERROR(INDEX('權數表原始_上櫃114Q4'!$CF:$CF,MATCH(VALUE($B100),'權數表原始_上櫃114Q4'!$A:$A,0)),"") | P100: =N100+O100 | Q100: =P100-IFERROR(INDEX('權數表原始_上櫃114Q4'!$CG:$CG,MATCH(VALUE($B100),'權數表原始_上櫃114Q4'!$A:$A,0)),"") | R100: 財務比率不佳(50)；營業收入、營業利益或稅前純益變動較大(26)；財務主管辭職(20)；董監事持股異動(10)；總經理質權設定達其實際持有股數五O%(5)
...

Sheet 權數表原始_上市114Q4
A1: 114年第四季本國上市公司平時管理權數統計表
A3: 產業類別：全部產業
A4: 公司代號 | B4: 公司名稱 | C4: 營運情形 | F4: 轉投資 | S4: 關係人交易 | AB4: 資金貸於他人與背書保證 | AF4: 財務比率 | AV4: 當季科目變動 | AZ4: 營收差異 | BA4: 最近三年度持續虧損 | BD4: 應收款逾期情形 | BE4: 財務權數 | BO4: 非財務權數 | CG4: 權數總計
C5: 1a.營業收入變動率 | D5: 1b.營業利益變動率 | E5: 1c.稅前純益變動率 | F5: 4a.採用權益法認列之關聯企業及合資損益之份額(損失)達當期營業利益之一定比率 | G5: 4b.子公司持有公司股權5%以上 | H5: 4c.採用權益法認列之關聯企業及合資損益之份額(損失)逾3億元以上者 | I5: 14.非流動性股權投資占權益之比重較高者 | J5: 當期非流動之股權投資增減金額占權益比重較高者 | K5: 採用其他會計師查核(核閱)之「子公司期末資產占總資產比率」 | L5: 採用其他會計師查核(核閱)之「子公司營業收入淨額占營收比率」 | M5: 採用其他會計師查核(核閱)之「採用權益法之投資期末餘額占總資產比率」 | N5: 採用其他會計師查核(核閱)之「採用權益法認列之關聯企業及合資損益份額占綜合損益比率」 | O5: 未經會計師查核(核閱)之「子公司期末資產占總資產比率」 | P5: 未經會計師查核(核閱)之「子公司綜合損益金額占綜合損益比率」 | Q5: 未經會計師查核(核閱)之「採用權益法之投資期末餘額占總資產比率」 | R5: 未經會計師查核(核閱)之「採用權益法認列之關聯企業及合資損益份額占綜合損益比率」 | S5: 5a.進貨金額占該科目之比率＞20% | T5: 5b.進貨金額較去年同期增加50％以上且金額達權益3％以上 | U5: 5c.銷貨金額占該科目之比率＞20% | V5: 5d.銷貨金額較去年同期增加50％以上且金額達權益3％以上 | W5: 5e.非屬進銷貨之資產交易金額╱期末總資產＞3% | X5: 6a.應收款項較上期增加50％以上且金額達權益3％或一億元者 | Y5: 6b.應收款項/權益>10％ | Z5: 7a.預付款項較上期增加50％以上且金額達權益3％或一億元者 | AA5: 7b.預付款項/權益>10％ | AB5: 8a.本季增加資金貸於他人金額達權益3％以上 | AC5: 期末資金貸於他人金額達權益10％以上 | AD5: 9a.本季增加背書保證金額＞權益之10% | AE5: 期末背書保證金額達權益30%以上 | AF5: 11a.負債比率＞60% | AG5: 負債比率較前期上升20％以上 | AH5: 11b.流動比率較前期下降20%以上 | AI5: 流動比率＜100% | AJ5: 應收帳款週轉率較前期下降20%以上 | AK5: 存貨週轉率較前期下降20%以上 | AL5: 現金流量比率較前期下降20%以上 | AM5: 當季現金流量比率為負數 | AN5: 權益報酬率較前期下降20%以上 | AO5: 質抵押資產比率(增列揭露事項) | AP5: 本年度應收款項占權益比率 | AQ5: 本年度應收款項占營業收入比率 | AR5: 本年度存貨占權益比率 | AS5: 本年度存貨占營業收入比率 | AT5: 本年度應收款項加計存貨占權益比率 | AU5: 本年度應收款項加計存貨占營業收入比率 | AV5: 約當現金占資本額70％且較上季增加逾30％ | AW5: 預付款項金額達5億元且較上季增加逾30％ | AX5: 預付款項佔權益10％以上且較上季增加逾30％ | AY5: 無形資產增減變動金額占總資產比率 | AZ5: 當季營收會計師查核(核閱)數與自結申報數差異比率 | BA5: 最近三年連續虧損 | BB5: 累計虧損占財務報告所列示股本比率達五○％以上者 | BC5: 每股淨值 | BD5: 應收款逾期一年以上占權益比率 | BE5: 營業收入、營業利益或稅前純益變動較大 | BF5: 採用權益法之關聯企業及合資損益份額(損失)金額達3億元以上，或占當期營業利益比率達20％以上或子公司持有公司股權5%以上 | BG5: 關係企業之交易 | BH5: 資金貸於他人 | BI5: 背書保證 | BJ5: 財務比率不佳 | BK5: 非流動之股權投資占權益比重較高 | BL5: 當期非流動之股權投資增減金額占權益比重較高者 | BM5: 每股淨值偏低 | BN5: 財務權數合計 | BO5: 財務主管辭職 | BP5: 會計主管辭職 | BQ5: 內稽主管辭職 | BR5: 研發主管辭職 | BS5: 更換會計師（非屬會計師事務所內部調整） | BT5: 董監事持股異動 | BU5: 董事長辭職 | BV5: 總經理辭職 | BW5: 獨立董事辭職 | BX5: 董事辭職 | BY5: 監察人辭職 | BZ5: 董監事報酬不合理 | CA5: 董事、監察人質權設定達全體董監實際持有股數五O%以上者 | CB5: 董事長質權設定達其實際持有股數五O%以上者 | CC5: 總經理質權設定達其實際持有股數五O%以上者 | CD5: 最近一年內有訴訟事件對公司財務業務有重大影響者 | CE5: 財務主管或會計主管或內稽主管是否與董事有二等親內之關係 | CF5: 權數總計
A6: 1101 | B6: 台泥 | C6: -3.11 | D6: -41.16 | E6: -141.3 | F6: 0 | G6: 0 | H6: -74.82 | I6: 16.19 | J6: -0.08 | K6: 0.18 | L6: 0 | M6: 0 | N6: 0 | O6: 0 | P6: 0 | Q6: 0 | R6: 0 | S6: 2.54 | T6: 0 | U6: 1.6 | V6: 0 | W6: 0.1 | X6: 0 | Y6: 0.65 | Z6: 0 | AA6: 0.01 | AB6: 0.93 | AC6: 22.48 | AD6: -1.11 | AE6: 35.37 | AF6: 50.29 | AG6: 4.53 | AH6: 3.27 | AI6: 207.29 | AJ6: -10.67 | AK6: -18.12 | AL6: 4.92 | AM6: 38.62 | AN6: -171.04 | AO6: 2.11 | AP6: 0.1 | AQ6: 0.19 | AR6: 0.07 | AS6: 0.13 | AT6: 0.16 | AU6: 0.32 | AV6: 116.32 | AW6: 9870265 | AX6: 3.37 | AY6: 0 | AZ6: -1.97 | BA6: 0 | BB6: -41.62 | BC6: 30.14 | BD6: 0 | BE6: 19 | BF6: 0 | BG6: 0 | BH6: 15 | BI6: 5 | BJ6: 15 | BK6: 0 | BL6: 0 | BM6: 0 | BN6: 54 | BO6: 0 | BP6: 0 | BQ6: 0 | BR6: 0 | BS6: 0 | BT6: 0 | BU6: 0 | BV6: 0 | BW6: 0 | BX6: 0 | BY6: 0 | BZ6: 0 | CA6: 0 | CB6: 0 | CC6: 0 | CD6: 0 | CE6: 0 | CF6: 0 | CG6: 54
A7: 1102 | B7: 亞泥 | C7: -6.89 | D7: 5.56 | E7: -21.82 | F7: 0 | G7: 0 | H7: -45.59 | I7: 51.02 | J7: 1.07 | K7: 0 | L7: 0 | M7: 0.05 | N7: -0.12 | O7: 0 | P7: 0 | Q7: 0 | R7: 0 | S7: 1.07 | T7: 0 | U7: 5.25 | V7: 0 | W7: 0.51 | X7: 0 | Y7: 0.36 | Z7: 0 | AA7: 0.01 | AB7: 2.28 | AC7: 3.29 | AD7: 0.06 | AE7: 24.87 | AF7: 37.22 | AG7: -2.74 | AH7: 9.48 | AI7: 160.28 | AJ7: -3.22 | AK7: -6.53 | AL7: -8.99 | AM7: 28.34 | AN7: -21.63 | AO7: 12.17 | AP7: 0.06 | AQ7: 0.17 | AR7: 0.04 | AS7: 0.1 | AT7: 0.09 | AU7: 0.27 | AV7: 36.6 | AW7: 1178948 | AX7: 0.58 | AY7: 0.07 | AZ7: -0.01 | BA7: 0 | BB7: -9.85 | BC7: 50.83 | BD7: 0 | BE7: 3 | BF7: 0 | BG7: 0 | BH7: 0 | BI7: 0 | BJ7: 5 | BK7: 30 | BL7: 0 | BM7: 0 | BN7: 38 | BO7: 0 | BP7: 0 | BQ7: 0 | BR7: 0 | BS7: 0 | BT7: 0 | BU7: 0 | BV7: 0 | BW7: 0 | BX7: 0 | BY7: 0 | BZ7: 0 | CA7: 0 | CB7: 0 | CC7: 0 | CD7: 0 | CE7: 0 | CF7: 0 | CG7: 38
A8: 1103 | B8: 嘉泥 | C8: 1 | D8: 47.22 | E8: 45 | F8: 0 | G8: 0.02 | H8: 179.96 | I8: 60.56 | J8: -0.21 | K8: 0 | L8: 0 | M8: 0 | N8: 0 | O8: 0 | P8: 0 | Q8: 0 | R8: 0 | S8: 45.16 | T8: 0 | U8: 2.56 | V8: 0 | W8: 0 | X8: 0 | Y8: 0.04 | Z8: 0 | AA8: 0 | AB8: 0 | AC8: 0 | AD8: -0.65 | AE8: 43.81 | AF8: 42.6 | AG8: 10.79 | AH8: -23.15 | AI8: 258.7 | AJ8: 19.09 | AK8: -30.64 | AL8: -44.16 | AM8: 7.84 | AN8: 83.66 | AO8: 19.71 | AP8: 0.01 | AQ8: 0.09 | AR8: 0.01 | AS8: 0.07 | AT8: 0.03 | AU8: 0.16 | AV8: 23.73 | AW8: 147237 | AX8: 0.79 | AY8: 0 | AZ8: 0 | BA8: 0 | BB8: 2.2 | BC8: 27.53 | BD8: 0 | BE8: 10 | BF8: 0 | BG8: 3 | BH8: 0 | BI8: 10 | BJ8: 25 | BK8: 30 | BL8: 0 | BM8: 0 | BN8: 78 | BO8: 0 | BP8: 0 | BQ8: 0 | BR8: 0 | BS8: 0 | BT8: 0 | BU8: 0 | BV8: 0 | BW8: 0 | BX8: 0 | BY8: 0 | BZ8: 0 | CA8: 0 | CB8: 0 | CC8: 0 | CD8: 0 | CE8: 0 | CF8: 0 | CG8: 78
A9: 1104 | B9: 環泥 | C9: -0.42 | D9: 15.22 | E9: 13.19 | F9: 0 | G9: 0 | H9: 9.89 | I9: 56 | J9: 2.13 | K9: 0.01 | L9: 0 | M9: 0 | N9: 0 | O9: 0 | P9: 0 | Q9: 0 | R9: 0 | S9: 6.63 | T9: 0 | U9: 0.19 | V9: 0 | W9: 0 | X9: 0 | Y9: 0.05 | Z9: 0 | AA9: 0 | AB9: 0 | AC9: 4.8 | AD9: 0.55 | AE9: 12.53 | AF9: 19.64 | AG9: 12.49 | AH9: -12.99 | AI9: 164.42 | AJ9: 1.7 | AK9: -13.37 | AL9: -45.36 | AM9: 27.47 | AN9: 12.33 | AO9: 0.05 | AP9: 0.08 | AQ9: 0.26 | AR9: 0.02 | AS9: 0.06 | AT9: 0.1 | AU9: 0.32 | AV9: 25.16 | AW9: 92726 | AX9: 0.37 | AY9: 0.96 | AZ9: -0.08 | BA9: 0 | BB9: 3.47 | BC9: 35.21 | BD9: 0 | BE9: 4 | BF9: 0 | BG9: 0 | BH9: 0 | BI9: 0 | BJ9: 10 | BK9: 30 | BL9: 0 | BM9: 0 | BN9: 44 | BO9: 0 | BP9: 0 | BQ9: 0 | BR9: 0 | BS9: 0 | BT9: 0 | BU9: 0 | BV9: 0 | BW9: 0 | BX9: 0 | BY9: 0 | BZ9: 0 | CA9: 0 | CB9: 0 | CC9: 0 | CD9: 0 | CE9: 0 | CF9: 0 | CG9: 44
A10: 1108 | B10: 幸福 | C10: -8.55 | D10: 73.84 | E10: 80.03 | F10: 0 | G10: 0 | H10: 0 | I10: 0.2 | J10: -0.01 | K10: 0 | L10: 0 | M10: 0 | N10: 0 | O10: 0 | P10: 0 | Q10: 0 | R10: 0 | S10: 14.52 | T10: 0 | U10: 1.52 | V10: 0 | W10: 0 | X10: 0 | Y10: 2.43 | Z10: 0 | AA10: 0 | AB10: 0 | AC10: 3.47 | AD10: 0 | AE10: 34.23 | AF10: 43.36 | AG10: -13.78 | AH10: -2.3 | AI10: 140.76 | AJ10: 7.97 | AK10: -8.18 | AL10: 26.22 | AM10: 27.44 | AN10: 67.19 | AO10: 59.28 | AP10: 0.15 | AQ10: 0.19 | AR10: 0.72 | AS10: 0.93 | AT10: 0.87 | AU10: 1.12 | AV10: 6.95 | AW10: 111115 | AX10: 1.93 | AY10: 0 | AZ10: 0.01 | BA10: 0 | BB10: 11.99 | BC10: 14.22 | BD10: 0 | BE10: 17 | BF10: 0 | BG10: 0 | BH10: 0 | BI10: 5 | BJ10: 0 | BK10: 0 | BL10: 0 | BM10: 0 | BN10: 22 | BO10: 0 | BP10: 0 | BQ10: 0 | BR10: 0 | BS10: 0 | BT10: 0 | BU10: 0 | BV10: 0 | BW10: 0 | BX10: 0 | BY10: 0 | BZ10: 0 | CA10: 0 | CB10: 0 | CC10: 0 | CD10: 0 | CE10: 0 | CF10: 0 | CG10: 22
A11: 1109 | B11: 信大 | C11: -4.83 | D11: -35.04 | E11: -25.66 | F11: 0 | G11: 0 | H11: 0 | I11: 2.15 | J11: -0.07 | K11: 0 | L11: 0 | M11: 0 | N11: 0 | O11: 0 | P11: 0 | Q11: 0 | R11: 0 | S11: 0 | T11: 0 | U11: 0 | V11: 0 | W11: 0 | X11: 0 | Y11: 0 | Z11: 0 | AA11: 0 | AB11: 0 | AC11: 0 | AD11: 0 | AE11: 5.18 | AF11: 10.13 | AG11: 6.07 | AH11: -17.11 | AI11: 580.01 | AJ11: -2.11 | AK11: 6.94 | AL11: 73.17 | AM11: 76.61 | AN11: -28.13 | AO11: 15.53 | AP11: 0.11 | AQ11: 0.25 | AR11: 0.08 | AS11: 0.19 | AT11: 0.19 | AU11: 0.43 | AV11: 69.2 | AW11: 67399 | AX11: 0.66 | AY11: 0.07 | AZ11: 2.04 | BA11: 0 | BB11: -5.35 | BC11: 24.52 | BD11: 0 | BE11: 7 | BF11: 0 | BG11: 0 | BH11: 0 | BI11: 0 | BJ11: 5 | BK11: 0 | BL11: 0 | BM11: 0 | BN11: 12 | BO11: 0 | BP11: 0 | BQ11: 0 | BR11: 0 | BS11: 0 | BT11: 0 | BU11: 0 | BV11: 0 | BW11: 0 | BX11: 0 | BY11: 0 | BZ11: 0 | CA11: 0 | CB11: 0 | CC11: 0 | CD11: 0 | CE11: 0 | CF11: 0 | CG11: 12
A12: 1110 | B12: 東泥 | C12: -0.74 | D12: -28.01 | E12: -35.2 | F12: 0 | G12: 0 | H12: -26.9 | I12: 22.41 | J12: -0.43 | K12: 0.01 | L12: 0 | M12: 0.04 | N12: 0.02 | O12: 0 | P12: 0 | Q12: 0 | R12: 0 | S12: 1.3 | T12: 0 | U12: 11.39 | V12: 0 | W12: 0 | X12: 0 | Y12: 0.55 | Z12: 0 | AA12: 0 | AB12: 2.07 | AC12: 2.07 | AD12: 0 | AE12: 6.33 | AF12: 26.16 | AG12: 5.44 | AH12: -4.43 | AI12: 142.75 | AJ12: -18.04 | AK12: -0.3 | AL12: -68.44 | AM12: 5.65 | AN12: -41.38 | AO12: 12.26 | AP12: 0.09 | AQ12: 0.32 | AR12: 0.13 | AS12: 0.45 | AT12: 0.23 | AU12: 0.76 | AV12: 10.81 | AW12: 84384 | AX12: 0.87 | AY12: 0 | AZ12: 0 | BA12: 0 | BB12: -2.67 | BC12: 16.6 | BD12: 0 | BE12: 7 | BF12: 0 | BG12: 0 | BH12: 0 | BI12: 0 | BJ12: 20 | BK12: 10 | BL12: 0 | BM12: 0 | BN12: 37 | BO12: 0 | BP12: 0 | BQ12: 0 | BR12: 0 | BS12: 0 | BT12: 0 | BU12: 0 | BV12: 0 | BW12: 0 | BX12: 0 | BY12: 0 | BZ12: 0 | CA12: 0 | CB12: 0 | CC12: 0 | CD12: 0 | CE12: 0 | CF12: 0 | CG12: 37
A13: 1201 | B13: 味全 | C13: -6.95 | D13: -37.49 | E13: -45.77 | F13: 0.08 | G13: 0 | H13: 0 | I13: 0.51 | J13: 0 | K13: 0 | L13: 0 | M13: 0 | N13: 0 | O13: 0 | P13: 0 | Q13: 0 | R13: 0 | S13: 9.13 | T13: 0 | U13: 2.96 | V13: 0 | W13: 0 | X13: 0 | Y13: 2.11 | Z13: 0 | AA13: 0 | AB13: 1.37 | AC13: 15.88 | AD13: 0.49 | AE13: 15.72 | AF13: 56.46 | AG13: 0.62 | AH13: -4.24 | AI13: 99.5 | AJ13: -7.18 | AK13: -6.27 | AL13: -32.4 | AM13: 17.69 | AN13: -55.16 | AO13: 24.57 | AP13: 0.35 | AQ13: 0.12 | AR13: 0.22 | AS13: 0.08 | AT13: 0.56 | AU13: 0.2 | AV13: 19.05 | AW13: 386176 | AX13: 5.03 | AY13: 0.06 | AZ13: 0 | BA13: 0 | BB13: -5.62 | BC13: 15.14 | BD13: 0 | BE13: 9 | BF13: 0 | BG13: 0 | BH13: 10 | BI13: 0 | BJ13: 30 | BK13: 0 | BL13: 0 | BM13: 0 | BN13: 49 | BO13: 0 | BP13: 0 | BQ13: 0 | BR13: 0 | BS13: 0 | BT13: 0 | BU13: 0 | BV13: 0 | BW13: 0 | BX13: 0 | BY13: 0 | BZ13: 0 | CA13: 0 | CB13: 0 | CC13: 0 | CD13: 0 | CE13: 0 | CF13: 0 | CG13: 49
A14: 1203 | B14: 味王 | C14: -10.06 | D14: -13 | E14: -20.82 | F14: 1.3 | G14: 0 | H14: -79.54 | I14: 4.64 | J14: 0.34 | K14: 0 | L14: 0 | M14: 0 | N14: -0.02 | O14: 0 | P14: 0 | Q14: 0 | R14: 0 | S14: 0 | T14: 0 | U14: 0.08 | V14: 0 | W14: 0 | X14: 0 | Y14: 0.09 | Z14: 0 | AA14: 0 | AB14: -0.01 | AC14: 1.43 | AD14: 0 | AE14: 24.86 | AF14: 29.2 | AG14: -2.18 | AH14: 8.43 | AI14: 291.33 | AJ14: -3.61 | AK14: -0.09 | AL14: 66.28 | AM14: 76.77 | AN14: -23.85 | AO14: 44.53 | AP14: 0.06 | AQ14: 0.08 | AR14: 0.17 | AS14: 0.22 | AT14: 0.23 | AU14: 0.3 | AV14: 91.19 | AW14: 66486 | AX14: 0.9 | AY14: 0 | AZ14: -0.06 | BA14: 0 | BB14: -10.34 | BC14: 26.84 | BD14: 0 | BE14: 7 | BF14: 0 | BG14: 0 | BH14: 0 | BI14: 0 | BJ14: 5 | BK14: 0 | BL14: 0 | BM14: 0 | BN14: 12 | BO14: 0 | BP14: 0 | BQ14: 0 | BR14: 0 | BS14: 0 | BT14: 0 | BU14: 0 | BV14: 0 | BW14: 0 | BX14: 0 | BY14: 0 | BZ14: 0 | CA14: 0 | CB14: 0 | CC14: 0 | CD14: 0 | CE14: 0 | CF14: 0 | CG14: 12
A15: 1210 | B15: 大成 | C15: -1.49 | D15: -10.79 | E15: -1.43 | F15: 0.9 | G15: 0.01 | H15: -239.69 | I15: 12.1 | J15: -0.28 | K15: 0 | L15: 0 | M15: 0 | N15: 0 | O15: 0 | P15: 0 | Q15: 0 | R15: 0 | S15: 1.72 | T15: 0 | U15: 0.52 | V15: 0 | W15: 0 | X15: 0 | Y15: 0.08 | Z15: 0 | AA15: 0 | AB15: 0.41 | AC15: 24.52 | AD15: 0.35 | AE15: 8.39 | AF15: 53.42 | AG15: 4.32 | AH15: -7.2 | AI15: 90.68 | AJ15: -4.11 | AK15: -8.21 | AL15: -25.78 | AM15: 18.34 | AN15: -7.96 | AO15: 0.02 | AP15: 0.25 | AQ15: 0.09 | AR15: 0.3 | AS15: 0.11 | AT15: 0.55 | AU15: 0.19 | AV15: 97.34 | AW15: 832994 | AX15: 2.35 | AY15: 0.01 | AZ15: -2.58 | BA15: 0 | BB15: -0.9 | BC15: 31.79 | BD15: 0 | BE15: 2 | BF15: 0 | BG15: 0 | BH15: 15 | BI15: 0 | BJ15: 15 | BK15: 0 | BL15: 0 | BM15: 0 | BN15: 32 | BO15: 0 | BP15: 0 | BQ15: 0 | BR15: 0 | BS15: 0 | BT15: 0 | BU15: 0 | BV15: 0 | BW15: 0 | BX15: 0 | BY15: 0 | BZ15: 0 | CA15: 0 | CB15: 0 | CC15: 0 | CD15: 0 | CE15: 0 | CF15: 0 | CG15: 32
A16: 1213 | B16: 大飲 | C16: 56.06 | D16: 43.62 | E16: -108.8 | F16: 0 | G16: 0 | H16: 0 | I16: 0 | J16: 0 | K16: 0 | L16: 0 | M16: 0 | N16: 0 | O16: 0 | P16: 0 | Q16: 0 | R16: 0 | S16: 9.24 | T16: 0 | U16: 84.17 | V16: 64.29 | W16: 0 | X16: 0 | Y16: 9.18 | Z16: 0 | AA16: 0 | AB16: 0 | AC16: 0 | AD16: 0 | AE16: 0 | AF16: 16.63 | AG16: 75.05 | AH16: -19.95 | AI16: 388.42 | AJ16: -36.79 | AK16: -13.32 | AL16: 82.61 | AM16: -84.43 | AN16: -106.77 | AO16: 18.41 | AP16: 0.08 | AQ16: 0.18 | AR16: 0.05 | AS16: 0.11 | AT16: 0.13 | AU16: 0.29 | AV16: 7.96 | AW16: 245797 | AX16: 37.68 | AY16: 0 | AZ16: 0 | BA16: 0 | BB16: -99.71 | BC16: 11.52 | BD16: 0 | BE16: 22 | BF16: 0 | BG16: 8 | BH16: 0 | BI16: 0 | BJ16: 40 | BK16: 0 | BL16: 0 | BM16: 0 | BN16: 70 | BO16: 0 | BP16: 20 | BQ16: 0 | BR16: 0 | BS16: 0 | BT16: 0 | BU16: 0 | BV16: 0 | BW16: 0 | BX16: 0 | BY16: 0 | BZ16: 0 | CA16: 0 | CB16: 0 | CC16: 0 | CD16: 0 | CE16: 0 | CF16: 20 | CG16: 90
A17: 1215 | B17: 卜蜂 | C17: 1.7 | D17: 63.64 | E17: 63.98 | F17: 0 | G17: 0 | H17: 239.74 | I17: 27.67 | J17: 0.52 | K17: 0 | L17: 0 | M17: 0 | N17: 0 | O17: 0 | P17: 0 | Q17: 0 | R17: 0 | S17: 1.7 | T17: 0 | U17: 0.86 | V17: 0 | W17: 0.23 | X17: 0 | Y17: 0.29 | Z17: 0 | AA17: 0 | AB17: 0 | AC17: 0 | AD17: 0 | AE17: 0 | AF17: 59.56 | AG17: -4.29 | AH17: 17.37 | AI17: 96.01 | AJ17: 1.81 | AK17: 0.88 | AL17: 6.68 | AM17: 38.49 | AN17: 44.26 | AO17: 0 | AP17: 0.23 | AQ17: 0.11 | AR17: 0.17 | AS17: 0.08 | AT17: 0.4 | AU17: 0.18 | AV17: 10.24 | AW17: 494664 | AX17: 3.84 | AY17: 0.01 | AZ17: 0 | BA17: 0 | BB17: 51.11 | BC17: 42.2 | BD17: 0 | BE17: 14 | BF17: 0 | BG17: 0 | BH17: 0 | BI17: 0 | BJ17: 10 | BK17: 10 | BL17: 0 | BM17: 0 | BN17: 34 | BO17: 0 | BP17: 0 | BQ17: 0 | BR17: 0 | BS17: 0 | BT17: 0 | BU17: 0 | BV17: 0 | BW17: 0 | BX17: 0 | BY17: 0 | BZ17: 0 | CA17: 0 | CB17: 0 | CC17: 0 | CD17: 0 | CE17: 0 | CF17: 0 | CG17: 34
... A959: 9958 | B959: 世紀鋼 | C959: 15.94 | D959: 11.3 | E959: 12.66 | F959: 0 | G959: 0 | H959: 0 | I959: 1.74 | J959: -0.26 | K959: 0 | L959: 0 | M959: 0 | N959: 0 | O959: 0 | P959: 0 | Q959: 0 | R959: 0 | S959: 0 | T959: 0 | U959: 0.91 | V959: 0 | W959: 0 | X959: 0 | Y959: 0 | Z959: 0 | AA959: 0 | AB959: 1.02 | AC959: 1.16 | AD959: 0 | AE959: 0 | AF959: 48.92 | AG959: 7.21 | AH959: -60.55 | AI959: 127.07 | AJ959: 62.57 | AK959: 19.93 | AL959: -16.19 | AM959: 49.13 | AN959: -7.12 | AO959: 50.19 | AP959: 0.03 | AQ959: 0.05 | AR959: 0.06 | AS959: 0.09 | AT959: 0.09 | AU959: 0.14 | AV959: 464.86 | AW959: 0 | AX959: 0 | AY959: 0.02 | AZ959: -0.03 | BA959: 0 | BB959: 15.05 | BC959: 45 | BD959: 0 | BE959: 6 | BF959: 0 | BG959: 0 | BH959: 0 | BI959: 0 | BJ959: 10 | BK959: 0 | BL959: 0 | BM959: 0 | BN959: 16 | BO959: 0 | BP959: 0 | BQ959: 0 | BR959: 0 | BS959: 0 | BT959: 0 | BU959: 0 | BV959: 0 | BW959: 0 | BX959: 0 | BY959: 0 | BZ959: 0 | CA959: 0 | CB959: 0 | CC959: 0 | CD959: 0 | CE959: 0 | CF959: 0 | CG959: 16
A961: 共954筆。

Sheet 權數表原始_上櫃114Q4
A1: 114年第四季上櫃公司平時管理權數統計表
A3: 產業類別：全部產業
A4: 公司代號 | B4: 公司名稱 | C4: 營運情形 | F4: 轉投資 | S4: 關係人交易 | AB4: 資金貸於他人與背書保證 | AF4: 財務比率 | AV4: 當季科目變動 | AZ4: 營收差異 | BA4: 最近三年度持續虧損 | BD4: 應收款逾期情形 | BE4: 財務權數 | BO4: 非財務權數 | CG4: 權數總計
C5: 1a.營業收入變動率 | D5: 1b.營業利益變動率 | E5: 1c.稅前純益變動率 | F5: 4a.採用權益法認列之關聯企業及合資損益之份額(損失)達當期營業利益之一定比率 | G5: 4b.子公司持有公司股權5%以上 | H5: 4c.採用權益法認列之關聯企業及合資損益之份額(損失)逾3億元以上者 | I5: 14.非流動性股權投資占權益之比重較高者 | J5: 當期非流動之股權投資增減金額占權益比重較高者 | K5: 採用其他會計師查核(核閱)之「子公司期末資產占總資產比率」 | L5: 採用其他會計師查核(核閱)之「子公司營業收入淨額占營收比率」 | M5: 採用其他會計師查核(核閱)之「採用權益法之投資期末餘額占總資產比率」 | N5: 採用其他會計師查核(核閱)之「採用權益法認列之關聯企業及合資損益份額占綜合損益比率」 | O5: 未經會計師查核(核閱)之「子公司期末資產占總資產比率」 | P5: 未經會計師查核(核閱)之「子公司綜合損益金額占綜合損益比率」 | Q5: 未經會計師查核(核閱)之「採用權益法之投資期末餘額占總資產比率」 | R5: 未經會計師查核(核閱)之「採用權益法認列之關聯企業及合資損益份額占綜合損益比率」 | S5: 5a.進貨金額占該科目之比率＞20% | T5: 5b.進貨金額較去年同期增加50％以上且金額達權益3％以上 | U5: 5c.銷貨金額占該科目之比率＞20% | V5: 5d.銷貨金額較去年同期增加50％以上且金額達權益3％以上 | W5: 5e.非屬進銷貨之資產交易金額╱期末總資產＞3% | X5: 6a.應收款項較上期增加50％以上且金額達權益3％或一億元者 | Y5: 6b.應收款項/權益>10％ | Z5: 7a.預付款項較上期增加50％以上且金額達權益3％或一億元者 | AA5: 7b.預付款項/權益>10％ | AB5: 8a.本季增加資金貸於他人金額達權益3％以上 | AC5: 期末資金貸於他人金額達權益10％以上 | AD5: 9a.本季增加背書保證金額＞權益之10% | AE5: 期末背書保證金額達權益30%以上 | AF5: 11a.負債比率＞60% | AG5: 負債比率較前期上升20％以上 | AH5: 11b.流動比率較前期下降20%以上 | AI5: 流動比率＜100% | AJ5: 應收帳款週轉率較前期下降20%以上 | AK5: 存貨週轉率較前期下降20%以上 | AL5: 現金流量比率較前期下降20%以上 | AM5: 當季現金流量比率為負數 | AN5: 權益報酬率較前期下降20%以上 | AO5: 質抵押資產比率(增列揭露事項) | AP5: 本年度應收款項占權益比率 | AQ5: 本年度應收款項占營業收入比率 | AR5: 本年度存貨占權益比率 | AS5: 本年度存貨占營業收入比率 | AT5: 本年度應收款項加計存貨占權益比率 | AU5: 本年度應收款項加計存貨占營業收入比率 | AV5: 約當現金占資本額70％且較上季增加逾30％ | AW5: 預付款項金額達5億元且較上季增加逾30％ | AX5: 預付款項佔權益10％以上且較上季增加逾30％ | AY5: 無形資產增減變動金額占總資產比率 | AZ5: 當季營收會計師查核(核閱)數與自結申報數差異比率 | BA5: 最近三年連續虧損 | BB5: 累計虧損占財務報告所列示股本比率達五○％以上者 | BC5: 每股淨值 | BD5: 應收款逾期一年以上占權益比率 | BE5: 營業收入、營業利益或稅前純益變動較大 | BF5: 採用權益法之關聯企業及合資損益份額(損失)金額達3億元以上，或占當期營業利益比率達20％以上或子公司持有公司股權5%以上 | BG5: 關係企業之交易 | BH5: 資金貸於他人 | BI5: 背書保證 | BJ5: 財務比率不佳 | BK5: 非流動之股權投資占權益比重較高 | BL5: 當期非流動之股權投資增減金額占權益比重較高者 | BM5: 每股淨值偏低 | BN5: 財務權數合計 | BO5: 財務主管辭職 | BP5: 會計主管辭職 | BQ5: 內稽主管辭職 | BR5: 研發主管辭職 | BS5: 更換會計師（非屬會計師事務所內部調整） | BT5: 董監事持股異動 | BU5: 董事長辭職 | BV5: 總經理辭職 | BW5: 獨立董事辭職 | BX5: 董事辭職 | BY5: 監察人辭職 | BZ5: 董監事報酬不合理 | CA5: 董事、監察人質權設定達全體董監實際持有股數五O%以上者 | CB5: 董事長質權設定達其實際持有股數五O%以上者 | CC5: 總經理質權設定達其實際持有股數五O%以上者 | CD5: 最近一年內有訴訟事件對公司財務業務有重大影響者 | CE5: 財務主管或會計主管或內稽主管是否與董事有二等親內之關係 | CF5: 權數總計
A6: 1240 | B6: 茂生農經 | C6: -3.96 | D6: -13.74 | E6: 9.76 | F6: 0 | G6: 0 | H6: 44.79 | I6: 31.25 | J6: 1.37 | K6: 0 | L6: 0 | M6: 0.22 | N6: 0.42 | O6: 0 | P6: 0 | Q6: 0 | R6: 0 | S6: 2.14 | T6: 0 | U6: 0.01 | V6: 0 | W6: 0 | X6: 0 | Y6: 0 | Z6: 0 | AA6: 0 | AB6: 0 | AC6: 0 | AD6: 0 | AE6: 8.95 | AF6: 29.65 | AG6: -1.92 | AH6: -4.6 | AI6: 194.62 | AJ6: -0.88 | AK6: 13.92 | AL6: 22.89 | AM6: 36.19 | AN6: 19.21 | AO6: 0 | AP6: 0.32 | AQ6: 0.18 | AR6: 0.1 | AS6: 0.06 | AT6: 0.42 | AU6: 0.24 | AV6: 35.34 | AW6: 31989 | AX6: 2.05 | AY6: 0 | AZ6: -0.01 | BA6: 0 | BB6: 4.54 | BC6: 33.97 | BD6: 0 | BE6: 2 | BF6: 0 | BG6: 0 | BH6: 0 | BI6: 0 | BJ6: 0 | BK6: 10 | BL6: 0 | BM6: 0 | BN6: 12 | BO6: 0 | BP6: 0 | BQ6: 0 | BR6: 0 | BS6: 0 | BT6: 0 | BU6: 0 | BV6: 0 | BW6: 0 | BX6: 0 | BY6: 0 | BZ6: 0 | CA6: 0 | CB6: 0 | CC6: 0 | CD6: 0 | CE6: 0 | CF6: 0 | CG6: 12
A7: 1259 | B7: 安心 | C7: 0.27 | D7: -217.25 | E7: -36.44 | F7: 0 | G7: 0 | H7: 657.96 | I7: 55.01 | J7: -6.93 | K7: 0 | L7: 0 | M7: 0 | N7: 0 | O7: 0 | P7: 0 | Q7: 0 | R7: 0 | S7: 51.55 | T7: 8.85 | U7: 0.04 | V7: 0 | W7: 2.88 | X7: 0 | Y7: 0.02 | Z7: 0 | AA7: 0 | AB7: 0 | AC7: 0 | AD7: 0 | AE7: 0 | AF7: 56.03 | AG7: -8.07 | AH7: -13.87 | AI7: 57.51 | AJ7: 15.63 | AK7: 1.65 | AL7: -3.29 | AM7: 38.2 | AN7: 29 | AO7: 0 | AP7: 0.04 | AQ7: 0.02 | AR7: 0.02 | AS7: 0.01 | AT7: 0.06 | AU7: 0.03 | AV7: 105.89 | AW7: 8631 | AX7: 0.29 | AY7: 0 | AZ7: -0.08 | BA7: 0 | BB7: -7.25 | BC7: 92.97 | BD7: 0 | BE7: 12 | BF7: 0 | BG7: 4 | BH7: 0 | BI7: 0 | BJ7: 20 | BK7: 30 | BL7: 0 | BM7: 0 | BN7: 66 | BO7: 0 | BP7: 0 | BQ7: 0 | BR7: 0 | BS7: 0 | BT7: 0 | BU7: 0 | BV7: 0 | BW7: 0 | BX7: 0 | BY7: 0 | BZ7: 0 | CA7: 0 | CB7: 0 | CC7: 0 | CD7: 0 | CE7: 0 | CF7: 0 | CG7: 66
A8: 1264 | B8: 德麥 | C8: -0.4 | D8: 0.56 | E8: -0.49 | F8: 0 | G8: 0 | H8: 90.82 | I8: 0.67 | J8: 0.03 | K8: 0 | L8: 0 | M8: 0 | N8: 0 | O8: 0 | P8: 0 | Q8: 0 | R8: 0 | S8: 5.63 | T8: 0 | U8: 1.21 | V8: 0 | W8: 0.02 | X8: 0 | Y8: 0.16 | Z8: 0 | AA8: 0.33 | AB8: 0.02 | AC8: 0.04 | AD8: 0 | AE8: 0 | AF8: 24.04 | AG8: 0 | AH8: -3.65 | AI8: 250.87 | AJ8: -2.2 | AK8: -5.08 | AL8: 21.91 | AM8: 77.62 | AN8: -8.52 | AO8: 5.9 | AP8: 0.25 | AQ8: 0.17 | AR8: 0.21 | AS8: 0.14 | AT8: 0.46 | AU8: 0.3 | AV8: 198.45 | AW8: 207214 | AX8: 4.6 | AY8: 0 | AZ8: 1.38 | BA8: 0 | BB8: -1.55 | BC8: 99.07 | BD8: 0 | BE8: 0 | BF8: 0 | BG8: 0 | BH8: 0 | BI8: 0 | BJ8: 0 | BK8: 0 | BL8: 0 | BM8: 0 | BN8: 0 | BO8: 0 | BP8: 0 | BQ8: 0 | BR8: 0 | BS8: 0 | BT8: 0 | BU8: 0 | BV8: 0 | BW8: 0 | BX8: 0 | BY8: 0 | BZ8: 0 | CA8: 0 | CB8: 0 | CC8: 0 | CD8: 0 | CE8: 0 | CF8: 0 | CG8: 0
A9: 1268 | B9: 漢來美食 | C9: 5.01 | D9: 0.19 | E9: 1.07 | F9: 0 | G9: 0 | H9: 0 | I9: 10.84 | J9: 0.01 | K9: 0 | L9: 0 | M9: 0 | N9: 0 | O9: 0 | P9: 0 | Q9: 0 | R9: 0 | S9: 0 | T9: 0 | U9: 0.32 | V9: 0 | W9: 0.04 | X9: 0 | Y9: 2.19 | Z9: 0 | AA9: 1.16 | AB9: 0 | AC9: 0 | AD9: 0 | AE9: 0 | AF9: 67.46 | AG9: -0.43 | AH9: -13.26 | AI9: 101.07 | AJ9: 22.53 | AK9: -0.21 | AL9: -9.32 | AM9: 45.17 | AN9: -2.76 | AO9: 15.33 | AP9: 0.08 | AQ9: 0.03 | AR9: 0.09 | AS9: 0.03 | AT9: 0.17 | AU9: 0.06 | AV9: 220.25 | AW9: 20785 | AX9: 0.9 | AY9: 0.01 | AZ9: 0 | BA9: 0 | BB9: 1.34 | BC9: 54.56 | BD9: 0 | BE9: 0 | BF9: 0 | BG9: 0 | BH9: 0 | BI9: 0 | BJ9: 10 | BK9: 0 | BL9: 0 | BM9: 0 | BN9: 10 | BO9: 0 | BP9: 0 | BQ9: 0 | BR9: 0 | BS9: 0 | BT9: 0 | BU9: 0 | BV9: 0 | BW9: 0 | BX9: 0 | BY9: 0 | BZ9: 0 | CA9: 0 | CB9: 0 | CC9: 0 | CD9: 0 | CE9: 0 | CF9: 0 | CG9: 10
A10: 1294 | B10: 漢田生技 | C10: 4.02 | D10: -12.4 | E10: -11.11 | F10: 0 | G10: 0 | H10: 0 | I10: 0 | J10: 0 | K10: 0 | L10: 0 | M10: 0 | N10: 0 | O10: 0 | P10: 0 | Q10: 0 | R10: 0 | S10: 0 | T10: 0 | U10: 0 | V10: 0 | W10: 0 | X10: 0 | Y10: 0 | Z10: 0 | AA10: 0 | AB10: 0 | AC10: 0 | AD10: 0 | AE10: 0 | AF10: 28.65 | AG10: 7.5 | AH10: -13.71 | AI10: 240 | AJ10: -20.58 | AK10: -9.42 | AL10: -16.91 | AM10: 65.17 | AN10: -33.82 | AO10: 52.61 | AP10: 0.16 | AQ10: 0.17 | AR10: 0.13 | AS10: 0.14 | AT10: 0.29 | AU10: 0.31 | AV10: 81.58 | AW10: 5090 | AX10: 0.61 | AY10: 0.06 | AZ10: 0 | BA10: 0 | BB10: -7.07 | BC10: 27.39 | BD10: 0 | BE10: 4 | BF10: 0 | BG10: 0 | BH10: 0 | BI10: 0 | BJ10: 15 | BK10: 0 | BL10: 0 | BM10: 0 | BN10: 19 | BO10: 0 | BP10: 20 | BQ10: 0 | BR10: 0 | BS10: 0 | BT10: 0 | BU10: 0 | BV10: 0 | BW10: 0 | BX10: 0 | BY10: 0 | BZ10: 0 | CA10: 0 | CB10: 0 | CC10: 0 | CD10: 0 | CE10: 0 | CF10: 20 | CG10: 39
A11: 1295 | B11: 生合 | C11: 4.97 | D11: -5.32 | E11: -14.47 | F11: 0 | G11: 0 | H11: 0 | I11: 0 | J11: 0 | K11: 0 | L11: 0 | M11: 0 | N11: 0 | O11: 0 | P11: 0 | Q11: 0 | R11: 0 | S11: 0 | T11: 0 | U11: 0.93 | V11: 0 | W11: 0 | X11: 0 | Y11: 0.2 | Z11: 0 | AA11: 0 | AB11: 0 | AC11: 0 | AD11: 0 | AE11: 0 | AF11: 56.89 | AG11: 5.43 | AH11: -35.36 | AI11: 120.37 | AJ11: 3.47 | AK11: -16.3 | AL11: -64.76 | AM11: 22.41 | AN11: -13.14 | AO11: 76.81 | AP11: 0.09 | AQ11: 0.11 | AR11: 0.18 | AS11: 0.23 | AT11: 0.26 | AU11: 0.34 | AV11: 78.3 | AW11: 0 | AX11: 0 | AY11: 0.01 | AZ11: 0.03 | BA11: 0 | BB11: -9.93 | BC11: 38.58 | BD11: 0 | BE11: 2 | BF11: 0 | BG11: 0 | BH11: 0 | BI11: 0 | BJ11: 30 | BK11: 0 | BL11: 0 | BM11: 0 | BN11: 32 | BO11: 0 | BP11: 0 | BQ11: 0 | BR11: 0 | BS11: 0 | BT11: 0 | BU11: 0 | BV11: 0 | BW11: 0 | BX11: 0 | BY11: 0 | BZ11: 0 | CA11: 0 | CB11: 0 | CC11: 0 | CD11: 0 | CE11: 0 | CF11: 0 | CG11: 32
A12: 1336 | B12: 台翰 | C12: -2.66 | D12: -49.31 | E12: -54.25 | F12: 0 | G12: 0 | H12: 0 | I12: 0.1 | J12: -0.01 | K12: 0 | L12: 0 | M12: 0 | N12: 0 | O12: 0 | P12: 0 | Q12: 0 | R12: 0 | S12: 0 | T12: 0 | U12: 10.21 | V12: 0 | W12: 0 | X12: 0 | Y12: 5.67 | Z12: 0 | AA12: 0 | AB12: -1.84 | AC12: 46.5 | AD12: 1.28 | AE12: 41.42 | AF12: 40.83 | AG12: 10.14 | AH12: -15.88 | AI12: 122.88 | AJ12: -8.09 | AK12: -7.09 | AL12: -14.62 | AM12: 22.96 | AN12: -67.01 | AO12: 9.21 | AP12: 0.26 | AQ12: 0.19 | AR12: 0.09 | AS12: 0.07 | AT12: 0.35 | AU12: 0.26 | AV12: 53.59 | AW12: 98105 | AX12: 5.28 | AY12: 0.02 | AZ12: 0 | BA12: 0 | BB12: -17.4 | BC12: 23.96 | BD12: 0 | BE12: 11 | BF12: 0 | BG12: 0 | BH12: 20 | BI12: 10 | BJ12: 10 | BK12: 0 | BL12: 0 | BM12: 0 | BN12: 51 | BO12: 0 | BP12: 0 | BQ12: 0 | BR12: 0 | BS12: 0 | BT12: 0 | BU12: 0 | BV12: 0 | BW12: 0 | BX12: 5 | BY12: 0 | BZ12: 0 | CA12: 0 | CB12: 0 | CC12: 0 | CD12: 0 | CE12: 0 | CF12: 5 | CG12: 56
A13: 1565 | B13: 精華 | C13: -9.52 | D13: -32.55 | E13: -38.79 | F13: 0 | G13: 0 | H13: 1304.81 | I13: 0.82 | J13: -0.17 | K13: 0 | L13: 0 | M13: 0 | N13: 0 | O13: 0 | P13: 0 | Q13: 0 | R13: 0 | S13: 0 | T13: 0 | U13: 0 | V13: 0 | W13: 0 | X13: 0 | Y13: 0 | Z13: 0 | AA13: 0 | AB13: 0 | AC13: 0 | AD13: 0 | AE13: 0 | AF13: 16.09 | AG13: -15.54 | AH13: 12.78 | AI13: 387.07 | AJ13: 2.25 | AK13: -9.87 | AL13: -26.72 | AM13: 56.18 | AN13: -41.04 | AO13: 25.4 | AP13: 0.08 | AQ13: 0.13 | AR13: 0.18 | AS13: 0.29 | AT13: 0.26 | AU13: 0.42 | AV13: 430.68 | AW13: 70353 | AX13: 1.07 | AY13: 0.01 | AZ13: 0 | BA13: 0 | BB13: -72.54 | BC13: 129.94 | BD13: 0 | BE13: 8 | BF13: 0 | BG13: 0 | BH13: 0 | BI13: 0 | BJ13: 15 | BK13: 0 | BL13: 0 | BM13: 0 | BN13: 23 | BO13: 0 | BP13: 0 | BQ13: 0 | BR13: 0 | BS13: 0 | BT13: 0 | BU13: 0 | BV13: 0 | BW13: 0 | BX13: 0 | BY13: 0 | BZ13: 0 | CA13: 0 | CB13: 0 | CC13: 0 | CD13: 0 | CE13: 0 | CF13: 0 | CG13: 23
A14: 1569 | B14: 濱川 | C14: 5.02 | D14: -30.78 | E14: -122.73 | F14: 0.23 | G14: 0 | H14: -567.86 | I14: 0.46 | J14: -0.82 | K14: 0 | L14: 0 | M14: 0 | N14: 0 | O14: 0 | P14: 0 | Q14: 0 | R14: 0 | S14: 0 | T14: 0 | U14: 0 | V14: 0 | W14: 0 | X14: 0 | Y14: 0 | Z14: 0 | AA14: 0 | AB14: 2.47 | AC14: 49.27 | AD14: 2.74 | AE14: 65.44 | AF14: 55.82 | AG14: 5.76 | AH14: -2.68 | AI14: 120.3 | AJ14: 17.42 | AK14: -10.48 | AL14: -281.14 | AM14: -14.98 | AN14: -146.49 | AO14: 0.63 | AP14: 0.44 | AQ14: 0.38 | AR14: 0.4 | AS14: 0.34 | AT14: 0.84 | AU14: 0.72 | AV14: 64.25 | AW14: 103498 | AX14: 3.7 | AY14: 0.05 | AZ14: 0 | BA14: 0 | BB14: -26.31 | BC14: 19.86 | BD14: 0 | BE14: 17 | BF14: 0 | BG14: 0 | BH14: 20 | BI14: 15 | BJ14: 35 | BK14: 0 | BL14: 0 | BM14: 0 | BN14: 87 | BO14: 0 | BP14: 0 | BQ14: 0 | BR14: 0 | BS14: 0 | BT14: 0 | BU14: 0 | BV14: 0 | BW14: 0 | BX14: 0 | BY14: 0 | BZ14: 0 | CA14: 0 | CB14: 0 | CC14: 0 | CD14: 0 | CE14: 0 | CF14: 0 | CG14: 87
A15: 1570 | B15: 力肯 | C15: -32.43 | D15: -69.56 | E15: -71.88 | F15: 0 | G15: 0 | H15: 0 | I15: 7.64 | J15: 1.21 | K15: 0 | L15: 0 | M15: 0 | N15: 0 | O15: 0 | P15: 0 | Q15: 0 | R15: 0 | S15: 0 | T15: 0 | U15: 0 | V15: 0 | W15: 0 | X15: 0 | Y15: 0 | Z15: 0 | AA15: 0 | AB15: 0.01 | AC15: 0.23 | AD15: 0 | AE15: 0 | AF15: 9.15 | AG15: -39.6 | AH15: 74.11 | AI15: 908.93 | AJ15: -37.96 | AK15: -33 | AL15: -79.77 | AM15: 13.02 | AN15: -75.31 | AO15: 23.81 | AP15: 0.09 | AQ15: 0.18 | AR15: 0.25 | AS15: 0.51 | AT15: 0.33 | AU15: 0.68 | AV15: 77.31 | AW15: 0 | AX15: 0 | AY15: 0.04 | AZ15: -0.25 | BA15: 0 | BB15: -19.43 | BC15: 19.71 | BD15: 0 | BE15: 19 | BF15: 0 | BG15: 0 | BH15: 0 | BI15: 0 | BJ15: 40 | BK15: 0 | BL15: 0 | BM15: 0 | BN15: 59 | BO15: 0 | BP15: 0 | BQ15: 0 | BR15: 0 | BS15: 20 | BT15: 0 | BU15: 0 | BV15: 0 | BW15: 10 | BX15: 0 | BY15: 0 | BZ15: 0 | CA15: 0 | CB15: 0 | CC15: 0 | CD15: 0 | CE15: 0 | CF15: 30 | CG15: 89
A16: 1580 | B16: 新麥 | C16: 1.82 | D16: -5.4 | E16: -10.02 | F16: 0 | G16: 0 | H16: 0 | I16: 0 | J16: 0 | K16: 0 | L16: 0 | M16: 0 | N16: 0 | O16: 0 | P16: 0 | Q16: 0 | R16: 0 | S16: 3.13 | T16: 0 | U16: 0.51 | V16: 0 | W16: 0 | X16: 0 | Y16: 0.02 | Z16: 0 | AA16: 0 | AB16: 0 | AC16: 0 | AD16: 0 | AE16: 0 | AF16: 25.85 | AG16: 0.12 | AH16: 9.49 | AI16: 298.75 | AJ16: -2.81 | AK16: -8.28 | AL16: 2.84 | AM16: 73.87 | AN16: -14.22 | AO16: 2.51 | AP16: 0.16 | AQ16: 0.11 | AR16: 0.28 | AS16: 0.19 | AT16: 0.44 | AU16: 0.3 | AV16: 232.8 | AW16: 37031 | AX16: 1.1 | AY16: 0.01 | AZ16: -0.37 | BA16: 0 | BB16: -22.15 | BC16: 65.12 | BD16: 0 | BE16: 2 | BF16: 0 | BG16: 0 | BH16: 0 | BI16: 0 | BJ16: 0 | BK16: 0 | BL16: 0 | BM16: 0 | BN16: 2 | BO16: 0 | BP16: 0 | BQ16: 0 | BR16: 0 | BS16: 0 | BT16: 0 | BU16: 0 | BV16: 0 | BW16: 0 | BX16: 0 | BY16: 0 | BZ16: 0 | CA16: 0 | CB16: 0 | CC16: 0 | CD16: 0 | CE16: 0 | CF16: 0 | CG16: 2
A17: 1584 | B17: 精剛 | C17: -9.94 | D17: -66.84 | E17: -70.72 | F17: 0 | G17: 0 | H17: -16.47 | I17: 16.42 | J17: 1.55 | K17: 0 | L17: 0 | M17: 0.02 | N17: 0.1 | O17: 0 | P17: 0 | Q17: 0 | R17: 0 | S17: 2.96 | T17: 0 | U17: 14.59 | V17: 0 | W17: 0 | X17: 0 | Y17: 0.75 | Z17: 0 | AA17: 0 | AB17: 0 | AC17: 0 | AD17: 0 | AE17: 1.05 | AF17: 39.75 | AG17: 12.16 | AH17: -30.31 | AI17: 160.42 | AJ17: 2.23 | AK17: -3.65 | AL17: 345.43 | AM17: 50.46 | AN17: -73.24 | AO17: 19.84 | AP17: 0.11 | AQ17: 0.2 | AR17: 0.42 | AS17: 0.78 | AT17: 0.53 | AU17: 0.98 | AV17: 23.84 | AW17: 313749 | AX17: 6.56 | AY17: 0.01 | AZ17: 0 | BA17: 0 | BB17: -10.93 | BC17: 20.98 | BD17: 0 | BE17: 15 | BF17: 0 | BG17: 0 | BH17: 0 | BI17: 0 | BJ17: 20 | BK17: 0 | BL17: 0 | BM17: 0 | BN17: 35 | BO17: 0 | BP17: 0 | BQ17: 10 | BR17: 0 | BS17: 0 | BT17: 0 | BU17: 0 | BV17: 0 | BW17: 0 | BX17: 0 | BY17: 0 | BZ17: 10 | CA17: 0 | CB17: 0 | CC17: 0 | CD17: 0 | CE17: 0 | CF17: 20 | CG17: 55
... A875: 9962 | B875: 有益 | C875: -21.01 | D875: -107.26 | E875: -124.1 | F875: 0 | G875: 0 | H875: 0 | I875: 0.74 | J875: 0.06 | K875: 0 | L875: 0 | M875: 0 | N875: 0 | O875: 0 | P875: 0 | Q875: 0 | R875: 0 | S875: 0 | T875: 0 | U875: 0 | V875: 0 | W875: 0 | X875: 0 | Y875: 0 | Z875: 0 | AA875: 0 | AB875: 0 | AC875: 0 | AD875: 0 | AE875: 0 | AF875: 33.79 | AG875: -4.9 | AH875: 3.32 | AI875: 220.17 | AJ875: -24.06 | AK875: -21.6 | AL875: 199.1 | AM875: 25.26 | AN875: -123.11 | AO875: 20.52 | AP875: 0.06 | AQ875: 0.03 | AR875: 0.88 | AS875: 0.48 | AT875: 0.94 | AU875: 0.51 | AV875: 15.24 | AW875: 23811 | AX875: 2.27 | AY875: 0.01 | AZ875: 0 | BA875: 0 | BB875: -10.58 | BC875: 11.65 | BD875: 0 | BE875: 24 | BF875: 0 | BG875: 0 | BH875: 0 | BI875: 0 | BJ875: 20 | BK875: 0 | BL875: 0 | BM875: 0 | BN875: 44 | BO875: 0 | BP875: 0 | BQ875: 0 | BR875: 0 | BS875: 0 | BT875: 0 | BU875: 0 | BV875: 0 | BW875: 0 | BX875: 0 | BY875: 0 | BZ875: 0 | CA875: 0 | CB875: 0 | CC875: 0 | CD875: 0 | CE875: 0 | CF875: 0 | CG875: 44
